Workbook

Sheet Overview
J2: Results
J3: 11 Sep to 2 Oct 2026
B6: ALL CALLS | E6: BETS | H6: LAYS
B7: =SUM('All Calls'!$N$6:$N$790) | E7: =SUMIFS('All Calls'!$N$6:$N$790,'All Calls'!$F$6:$F$790,"Bet") | H7: =SUMIFS('All Calls'!$N$6:$N$790,'All Calls'!$F$6:$F$790,"Lay")
B9: =COUNTIFS('All Calls'!$M$6:$M$790,"Win")+COUNTIFS('All Calls'!$M$6:$M$790,"Loss")&" settled, "&TEXT(COUNTIFS('All Calls'!$M$6:$M$790,"Win")/(COUNTIFS('All Calls'!$M$6:$M$790,"Win")+COUNTIFS('All Calls'!$M$6:$M$790,"Loss")),"0%")&" strike, "&TEXT(IF(SUM('All Calls'!$O$6:$O$790)=0,0,B7/SUM('All Calls'!$O$6:$O$790)),"+0.0%;-0.0%")&" ROI" | E9: =COUNTIFS('All Calls'!$M$6:$M$790,"Win",'All Calls'!$F$6:$F$790,"Bet")+COUNTIFS('All Calls'!$M$6:$M$790,"Loss",'All Calls'!$F$6:$F$790,"Bet")&" settled, "&TEXT(COUNTIFS('All Calls'!$M$6:$M$790,"Win",'All Calls'!$F$6:$F$790,"Bet")/(COUNTIFS('All Calls'!$M$6:$M$790,"Win",'All Calls'!$F$6:$F$790,"Bet")+COUNTIFS('All Calls'!$M$6:$M$790,"Loss",'All Calls'!$F$6:$F$790,"Bet")),"0%")&" strike, "&TEXT(IF(SUMIFS('All Calls'!$O$6:$O$790,'All Calls'!$F$6:$F$790,"Bet")=0,0,E7/SUMIFS('All Calls'!$O$6:$O$790,'All Calls'!$F$6:$F$790,"Bet")),"+0.0%;-0.0%")&" ROI" | H9: =COUNTIFS('All Calls'!$M$6:$M$790,"Win",'All Calls'!$F$6:$F$790,"Lay")+COUNTIFS('All Calls'!$M$6:$M$790,"Loss",'All Calls'!$F$6:$F$790,"Lay")&" settled, "&TEXT(COUNTIFS('All Calls'!$M$6:$M$790,"Win",'All Calls'!$F$6:$F$790,"Lay")/(COUNTIFS('All Calls'!$M$6:$M$790,"Win",'All Calls'!$F$6:$F$790,"Lay")+COUNTIFS('All Calls'!$M$6:$M$790,"Loss",'All Calls'!$F$6:$F$790,"Lay")),"0%")&" strike, "&TEXT(IF(SUMIFS('All Calls'!$O$6:$O$790,'All Calls'!$F$6:$F$790,"Lay")=0,0,H7/SUMIFS('All Calls'!$O$6:$O$790,'All Calls'!$F$6:$F$790,"Lay")),"+0.0%;-0.0%")&" ROI"
A11: Level stakes: one unit a call, a tenth on a Way. Bets settle at the best of fixed odds, SP and BSP; lays at the shortest lay price or BSP.
A12: A lay wins one unit when the horse loses and risks the price less one. ROI is profit over units at risk. Scratchings and abandoned races are void.
A13: Bets at $10 or more from 11 to 15 Sep are excluded: our ratings over-priced long shots until the 15 Sep fix.
A14: BY CALL
B15: Calls | C15: Won | D15: Lost | E15: Void | F15: Pending | G15: Strike | H15: Profit (u) | I15: At risk (u) | J15: ROI
A16: All calls | B16: =COUNTIFS('All Calls'!$M$6:$M$790,"<>") | C16: =COUNTIFS('All Calls'!$M$6:$M$790,"Win") | D16: =COUNTIFS('All Calls'!$M$6:$M$790,"Loss") | E16: =COUNTIFS('All Calls'!$M$6:$M$790,"Void") | F16: =COUNTIFS('All Calls'!$M$6:$M$790,"Pending") | G16: =IF(C16+D16=0,"",C16/(C16+D16)) | H16: =SUM('All Calls'!$N$6:$N$790) | I16: =SUM('All Calls'!$O$6:$O$790) | J16: =IF(I16=0,"",H16/I16)
A17: Bets | B17: =COUNTIFS('All Calls'!$M$6:$M$790,"<>",'All Calls'!$F$6:$F$790,"Bet") | C17: =COUNTIFS('All Calls'!$M$6:$M$790,"Win",'All Calls'!$F$6:$F$790,"Bet") | D17: =COUNTIFS('All Calls'!$M$6:$M$790,"Loss",'All Calls'!$F$6:$F$790,"Bet") | E17: =COUNTIFS('All Calls'!$M$6:$M$790,"Void",'All Calls'!$F$6:$F$790,"Bet") | F17: =COUNTIFS('All Calls'!$M$6:$M$790,"Pending",'All Calls'!$F$6:$F$790,"Bet") | G17: =IF(C17+D17=0,"",C17/(C17+D17)) | H17: =SUMIFS('All Calls'!$N$6:$N$790,'All Calls'!$F$6:$F$790,"Bet") | I17: =SUMIFS('All Calls'!$O$6:$O$790,'All Calls'!$F$6:$F$790,"Bet") | J17: =IF(I17=0,"",H17/I17)
A18: Lays | B18: =COUNTIFS('All Calls'!$M$6:$M$790,"<>",'All Calls'!$F$6:$F$790,"Lay") | C18: =COUNTIFS('All Calls'!$M$6:$M$790,"Win",'All Calls'!$F$6:$F$790,"Lay") | D18: =COUNTIFS('All Calls'!$M$6:$M$790,"Loss",'All Calls'!$F$6:$F$790,"Lay") | E18: =COUNTIFS('All Calls'!$M$6:$M$790,"Void",'All Calls'!$F$6:$F$790,"Lay") | F18: =COUNTIFS('All Calls'!$M$6:$M$790,"Pending",'All Calls'!$F$6:$F$790,"Lay") | G18: =IF(C18+D18=0,"",C18/(C18+D18)) | H18: =SUMIFS('All Calls'!$N$6:$N$790,'All Calls'!$F$6:$F$790,"Lay") | I18: =SUMIFS('All Calls'!$O$6:$O$790,'All Calls'!$F$6:$F$790,"Lay") | J18: =IF(I18=0,"",H18/I18)
A20: BY TAG
A21: Tag | B21: Calls | C21: Won | D21: Lost | E21: Void | F21: Pending | G21: Strike | H21: Profit (u) | I21: At risk (u) | J21: ROI
A22: Prime | B22: =COUNTIFS('All Calls'!$M$6:$M$790,"<>",'All Calls'!$G$6:$G$790,"Prime") | C22: =COUNTIFS('All Calls'!$M$6:$M$790,"Win",'All Calls'!$G$6:$G$790,"Prime") | D22: =COUNTIFS('All Calls'!$M$6:$M$790,"Loss",'All Calls'!$G$6:$G$790,"Prime") | E22: =COUNTIFS('All Calls'!$M$6:$M$790,"Void",'All Calls'!$G$6:$G$790,"Prime") | F22: =COUNTIFS('All Calls'!$M$6:$M$790,"Pending",'All Calls'!$G$6:$G$790,"Prime") | G22: =IF(C22+D22=0,"",C22/(C22+D22)) | H22: =SUMIFS('All Calls'!$N$6:$N$790,'All Calls'!$G$6:$G$790,"Prime") | I22: =SUMIFS('All Calls'!$O$6:$O$790,'All Calls'!$G$6:$G$790,"Prime") | J22: =IF(I22=0,"",H22/I22)
A23: Bet | B23: =COUNTIFS('All Calls'!$M$6:$M$790,"<>",'All Calls'!$G$6:$G$790,"Bet") | C23: =COUNTIFS('All Calls'!$M$6:$M$790,"Win",'All Calls'!$G$6:$G$790,"Bet") | D23: =COUNTIFS('All Calls'!$M$6:$M$790,"Loss",'All Calls'!$G$6:$G$790,"Bet") | E23: =COUNTIFS('All Calls'!$M$6:$M$790,"Void",'All Calls'!$G$6:$G$790,"Bet") | F23: =COUNTIFS('All Calls'!$M$6:$M$790,"Pending",'All Calls'!$G$6:$G$790,"Bet") | G23: =IF(C23+D23=0,"",C23/(C23+D23)) | H23: =SUMIFS('All Calls'!$N$6:$N$790,'All Calls'!$G$6:$G$790,"Bet") | I23: =SUMIFS('All Calls'!$O$6:$O$790,'All Calls'!$G$6:$G$790,"Bet") | J23: =IF(I23=0,"",H23/I23)
A24: Way | B24: =COUNTIFS('All Calls'!$M$6:$M$790,"<>",'All Calls'!$G$6:$G$790,"Way") | C24: =COUNTIFS('All Calls'!$M$6:$M$790,"Win",'All Calls'!$G$6:$G$790,"Way") | D24: =COUNTIFS('All Calls'!$M$6:$M$790,"Loss",'All Calls'!$G$6:$G$790,"Way") | E24: =COUNTIFS('All Calls'!$M$6:$M$790,"Void",'All Calls'!$G$6:$G$790,"Way") | F24: =COUNTIFS('All Calls'!$M$6:$M$790,"Pending",'All Calls'!$G$6:$G$790,"Way") | G24: =IF(C24+D24=0,"",C24/(C24+D24)) | H24: =SUMIFS('All Calls'!$N$6:$N$790,'All Calls'!$G$6:$G$790,"Way") | I24: =SUMIFS('All Calls'!$O$6:$O$790,'All Calls'!$G$6:$G$790,"Way") | J24: =IF(I24=0,"",H24/I24)
A25: Lay | B25: =COUNTIFS('All Calls'!$M$6:$M$790,"<>",'All Calls'!$G$6:$G$790,"Lay") | C25: =COUNTIFS('All Calls'!$M$6:$M$790,"Win",'All Calls'!$G$6:$G$790,"Lay") | D25: =COUNTIFS('All Calls'!$M$6:$M$790,"Loss",'All Calls'!$G$6:$G$790,"Lay") | E25: =COUNTIFS('All Calls'!$M$6:$M$790,"Void",'All Calls'!$G$6:$G$790,"Lay") | F25: =COUNTIFS('All Calls'!$M$6:$M$790,"Pending",'All Calls'!$G$6:$G$790,"Lay") | G25: =IF(C25+D25=0,"",C25/(C25+D25)) | H25: =SUMIFS('All Calls'!$N$6:$N$790,'All Calls'!$G$6:$G$790,"Lay") | I25: =SUMIFS('All Calls'!$O$6:$O$790,'All Calls'!$G$6:$G$790,"Lay") | J25: =IF(I25=0,"",H25/I25)
A27: BY WEEK
A28: Week of | B28: Calls | C28: Won | D28: Lost | E28: Void | F28: Pending | G28: Strike | H28: Profit (u) | I28: At risk (u) | J28: ROI
A29: 46272 | B29: =COUNTIFS('All Calls'!$M$6:$M$790,"<>",'All Calls'!$A$6:$A$790,">="&$A29,'All Calls'!$A$6:$A$790,"<"&($A29+7)) | C29: =COUNTIFS('All Calls'!$M$6:$M$790,"Win",'All Calls'!$A$6:$A$790,">="&$A29,'All Calls'!$A$6:$A$790,"<"&($A29+7)) | D29: =COUNTIFS('All Calls'!$M$6:$M$790,"Loss",'All Calls'!$A$6:$A$790,">="&$A29,'All Calls'!$A$6:$A$790,"<"&($A29+7)) | E29: =COUNTIFS('All Calls'!$M$6:$M$790,"Void",'All Calls'!$A$6:$A$790,">="&$A29,'All Calls'!$A$6:$A$790,"<"&($A29+7)) | F29: =COUNTIFS('All Calls'!$M$6:$M$790,"Pending",'All Calls'!$A$6:$A$790,">="&$A29,'All Calls'!$A$6:$A$790,"<"&($A29+7)) | G29: =IF(C29+D29=0,"",C29/(C29+D29)) | H29: =SUMIFS('All Calls'!$N$6:$N$790,'All Calls'!$A$6:$A$790,">="&$A29,'All Calls'!$A$6:$A$790,"<"&($A29+7)) | I29: =SUMIFS('All Calls'!$O$6:$O$790,'All Calls'!$A$6:$A$790,">="&$A29,'All Calls'!$A$6:$A$790,"<"&($A29+7)) | J29: =IF(I29=0,"",H29/I29)
A30: 46279 | B30: =COUNTIFS('All Calls'!$M$6:$M$790,"<>",'All Calls'!$A$6:$A$790,">="&$A30,'All Calls'!$A$6:$A$790,"<"&($A30+7)) | C30: =COUNTIFS('All Calls'!$M$6:$M$790,"Win",'All Calls'!$A$6:$A$790,">="&$A30,'All Calls'!$A$6:$A$790,"<"&($A30+7)) | D30: =COUNTIFS('All Calls'!$M$6:$M$790,"Loss",'All Calls'!$A$6:$A$790,">="&$A30,'All Calls'!$A$6:$A$790,"<"&($A30+7)) | E30: =COUNTIFS('All Calls'!$M$6:$M$790,"Void",'All Calls'!$A$6:$A$790,">="&$A30,'All Calls'!$A$6:$A$790,"<"&($A30+7)) | F30: =COUNTIFS('All Calls'!$M$6:$M$790,"Pending",'All Calls'!$A$6:$A$790,">="&$A30,'All Calls'!$A$6:$A$790,"<"&($A30+7)) | G30: =IF(C30+D30=0,"",C30/(C30+D30)) | H30: =SUMIFS('All Calls'!$N$6:$N$790,'All Calls'!$A$6:$A$790,">="&$A30,'All Calls'!$A$6:$A$790,"<"&($A30+7)) | I30: =SUMIFS('All Calls'!$O$6:$O$790,'All Calls'!$A$6:$A$790,">="&$A30,'All Calls'!$A$6:$A$790,"<"&($A30+7)) | J30: =IF(I30=0,"",H30/I30)
A31: 46286 | B31: =COUNTIFS('All Calls'!$M$6:$M$790,"<>",'All Calls'!$A$6:$A$790,">="&$A31,'All Calls'!$A$6:$A$790,"<"&($A31+7)) | C31: =COUNTIFS('All Calls'!$M$6:$M$790,"Win",'All Calls'!$A$6:$A$790,">="&$A31,'All Calls'!$A$6:$A$790,"<"&($A31+7)) | D31: =COUNTIFS('All Calls'!$M$6:$M$790,"Loss",'All Calls'!$A$6:$A$790,">="&$A31,'All Calls'!$A$6:$A$790,"<"&($A31+7)) | E31: =COUNTIFS('All Calls'!$M$6:$M$790,"Void",'All Calls'!$A$6:$A$790,">="&$A31,'All Calls'!$A$6:$A$790,"<"&($A31+7)) | F31: =COUNTIFS('All Calls'!$M$6:$M$790,"Pending",'All Calls'!$A$6:$A$790,">="&$A31,'All Calls'!$A$6:$A$790,"<"&($A31+7)) | G31: =IF(C31+D31=0,"",C31/(C31+D31)) | H31: =SUMIFS('All Calls'!$N$6:$N$790,'All Calls'!$A$6:$A$790,">="&$A31,'All Calls'!$A$6:$A$790,"<"&($A31+7)) | I31: =SUMIFS('All Calls'!$O$6:$O$790,'All Calls'!$A$6:$A$790,">="&$A31,'All Calls'!$A$6:$A$790,"<"&($A31+7)) | J31: =IF(I31=0,"",H31/I31)
A32: 46293 | B32: =COUNTIFS('All Calls'!$M$6:$M$790,"<>",'All Calls'!$A$6:$A$790,">="&$A32,'All Calls'!$A$6:$A$790,"<"&($A32+7)) | C32: =COUNTIFS('All Calls'!$M$6:$M$790,"Win",'All Calls'!$A$6:$A$790,">="&$A32,'All Calls'!$A$6:$A$790,"<"&($A32+7)) | D32: =COUNTIFS('All Calls'!$M$6:$M$790,"Loss",'All Calls'!$A$6:$A$790,">="&$A32,'All Calls'!$A$6:$A$790,"<"&($A32+7)) | E32: =COUNTIFS('All Calls'!$M$6:$M$790,"Void",'All Calls'!$A$6:$A$790,">="&$A32,'All Calls'!$A$6:$A$790,"<"&($A32+7)) | F32: =COUNTIFS('All Calls'!$M$6:$M$790,"Pending",'All Calls'!$A$6:$A$790,">="&$A32,'All Calls'!$A$6:$A$790,"<"&($A32+7)) | G32: =IF(C32+D32=0,"",C32/(C32+D32)) | H32: =SUMIFS('All Calls'!$N$6:$N$790,'All Calls'!$A$6:$A$790,">="&$A32,'All Calls'!$A$6:$A$790,"<"&($A32+7)) | I32: =SUMIFS('All Calls'!$O$6:$O$790,'All Calls'!$A$6:$A$790,">="&$A32,'All Calls'!$A$6:$A$790,"<"&($A32+7)) | J32: =IF(I32=0,"",H32/I32)
A34: BY DAY
A35: Date | B35: Settled | C35: Bets (u) | D35: Lays (u) | E35: Day (u) | F35: Running (u)
A36: 46276 | B36: =COUNTIFS('All Calls'!$A$6:$A$790,$A36,'All Calls'!$M$6:$M$790,"<>Pending") | C36: =SUMIFS('All Calls'!$N$6:$N$790,'All Calls'!$A$6:$A$790,$A36,'All Calls'!$F$6:$F$790,"Bet") | D36: =SUMIFS('All Calls'!$N$6:$N$790,'All Calls'!$A$6:$A$790,$A36,'All Calls'!$F$6:$F$790,"Lay") | E36: =C36+D36 | F36: =E36
A37: 46277 | B37: =COUNTIFS('All Calls'!$A$6:$A$790,$A37,'All Calls'!$M$6:$M$790,"<>Pending") | C37: =SUMIFS('All Calls'!$N$6:$N$790,'All Calls'!$A$6:$A$790,$A37,'All Calls'!$F$6:$F$790,"Bet") | D37: =SUMIFS('All Calls'!$N$6:$N$790,'All Calls'!$A$6:$A$790,$A37,'All Calls'!$F$6:$F$790,"Lay") | E37: =C37+D37 | F37: =F36+E37
A38: 46278 | B38: =COUNTIFS('All Calls'!$A$6:$A$790,$A38,'All Calls'!$M$6:$M$790,"<>Pending") | C38: =SUMIFS('All Calls'!$N$6:$N$790,'All Calls'!$A$6:$A$790,$A38,'All Calls'!$F$6:$F$790,"Bet") | D38: =SUMIFS('All Calls'!$N$6:$N$790,'All Calls'!$A$6:$A$790,$A38,'All Calls'!$F$6:$F$790,"Lay") | E38: =C38+D38 | F38: =F37+E38
A39: 46279 | B39: =COUNTIFS('All Calls'!$A$6:$A$790,$A39,'All Calls'!$M$6:$M$790,"<>Pending") | C39: =SUMIFS('All Calls'!$N$6:$N$790,'All Calls'!$A$6:$A$790,$A39,'All Calls'!$F$6:$F$790,"Bet") | D39: =SUMIFS('All Calls'!$N$6:$N$790,'All Calls'!$A$6:$A$790,$A39,'All Calls'!$F$6:$F$790,"Lay") | E39: =C39+D39 | F39: =F38+E39
A40: 46280 | B40: =COUNTIFS('All Calls'!$A$6:$A$790,$A40,'All Calls'!$M$6:$M$790,"<>Pending") | C40: =SUMIFS('All Calls'!$N$6:$N$790,'All Calls'!$A$6:$A$790,$A40,'All Calls'!$F$6:$F$790,"Bet") | D40: =SUMIFS('All Calls'!$N$6:$N$790,'All Calls'!$A$6:$A$790,$A40,'All Calls'!$F$6:$F$790,"Lay") | E40: =C40+D40 | F40: =F39+E40
A41: 46281 | B41: =COUNTIFS('All Calls'!$A$6:$A$790,$A41,'All Calls'!$M$6:$M$790,"<>Pending") | C41: =SUMIFS('All Calls'!$N$6:$N$790,'All Calls'!$A$6:$A$790,$A41,'All Calls'!$F$6:$F$790,"Bet") | D41: =SUMIFS('All Calls'!$N$6:$N$790,'All Calls'!$A$6:$A$790,$A41,'All Calls'!$F$6:$F$790,"Lay") | E41: =C41+D41 | F41: =F40+E41
A42: 46282 | B42: =COUNTIFS('All Calls'!$A$6:$A$790,$A42,'All Calls'!$M$6:$M$790,"<>Pending") | C42: =SUMIFS('All Calls'!$N$6:$N$790,'All Calls'!$A$6:$A$790,$A42,'All Calls'!$F$6:$F$790,"Bet") | D42: =SUMIFS('All Calls'!$N$6:$N$790,'All Calls'!$A$6:$A$790,$A42,'All Calls'!$F$6:$F$790,"Lay") | E42: =C42+D42 | F42: =F41+E42
A43: 46283 | B43: =COUNTIFS('All Calls'!$A$6:$A$790,$A43,'All Calls'!$M$6:$M$790,"<>Pending") | C43: =SUMIFS('All Calls'!$N$6:$N$790,'All Calls'!$A$6:$A$790,$A43,'All Calls'!$F$6:$F$790,"Bet") | D43: =SUMIFS('All Calls'!$N$6:$N$790,'All Calls'!$A$6:$A$790,$A43,'All Calls'!$F$6:$F$790,"Lay") | E43: =C43+D43 | F43: =F42+E43
A44: 46284 | B44: =COUNTIFS('All Calls'!$A$6:$A$790,$A44,'All Calls'!$M$6:$M$790,"<>Pending") | C44: =SUMIFS('All Calls'!$N$6:$N$790,'All Calls'!$A$6:$A$790,$A44,'All Calls'!$F$6:$F$790,"Bet") | D44: =SUMIFS('All Calls'!$N$6:$N$790,'All Calls'!$A$6:$A$790,$A44,'All Calls'!$F$6:$F$790,"Lay") | E44: =C44+D44 | F44: =F43+E44
A45: 46285 | B45: =COUNTIFS('All Calls'!$A$6:$A$790,$A45,'All Calls'!$M$6:$M$790,"<>Pending") | C45: =SUMIFS('All Calls'!$N$6:$N$790,'All Calls'!$A$6:$A$790,$A45,'All Calls'!$F$6:$F$790,"Bet") | D45: =SUMIFS('All Calls'!$N$6:$N$790,'All Calls'!$A$6:$A$790,$A45,'All Calls'!$F$6:$F$790,"Lay") | E45: =C45+D45 | F45: =F44+E45
A46: 46286 | B46: =COUNTIFS('All Calls'!$A$6:$A$790,$A46,'All Calls'!$M$6:$M$790,"<>Pending") | C46: =SUMIFS('All Calls'!$N$6:$N$790,'All Calls'!$A$6:$A$790,$A46,'All Calls'!$F$6:$F$790,"Bet") | D46: =SUMIFS('All Calls'!$N$6:$N$790,'All Calls'!$A$6:$A$790,$A46,'All Calls'!$F$6:$F$790,"Lay") | E46: =C46+D46 | F46: =F45+E46
A47: 46287 | B47: =COUNTIFS('All Calls'!$A$6:$A$790,$A47,'All Calls'!$M$6:$M$790,"<>Pending") | C47: =SUMIFS('All Calls'!$N$6:$N$790,'All Calls'!$A$6:$A$790,$A47,'All Calls'!$F$6:$F$790,"Bet") | D47: =SUMIFS('All Calls'!$N$6:$N$790,'All Calls'!$A$6:$A$790,$A47,'All Calls'!$F$6:$F$790,"Lay") | E47: =C47+D47 | F47: =F46+E47
A48: 46288 | B48: =COUNTIFS('All Calls'!$A$6:$A$790,$A48,'All Calls'!$M$6:$M$790,"<>Pending") | C48: =SUMIFS('All Calls'!$N$6:$N$790,'All Calls'!$A$6:$A$790,$A48,'All Calls'!$F$6:$F$790,"Bet") | D48: =SUMIFS('All Calls'!$N$6:$N$790,'All Calls'!$A$6:$A$790,$A48,'All Calls'!$F$6:$F$790,"Lay") | E48: =C48+D48 | F48: =F47+E48
... A57: 46297 | B57: =COUNTIFS('All Calls'!$A$6:$A$790,$A57,'All Calls'!$M$6:$M$790,"<>Pending") | C57: =SUMIFS('All Calls'!$N$6:$N$790,'All Calls'!$A$6:$A$790,$A57,'All Calls'!$F$6:$F$790,"Bet") | D57: =SUMIFS('All Calls'!$N$6:$N$790,'All Calls'!$A$6:$A$790,$A57,'All Calls'!$F$6:$F$790,"Lay") | E57: =C57+D57 | F57: =F56+E57
A59: theoverlay.com.au 18+ Gamble responsibly: 1800 858 858

Sheet All Calls
O2: All calls
O3: Every bet and lay, 11 Sep to 2 Oct 2026
A5: Date | B5: Track | C5: Race | D5: No. | E5: Horse | F5: Call | G5: Tag | H5: Rated $ | I5: Price $ | J5: Edge | K5: Stake (u) | L5: Finish | M5: Result | N5: Profit (u) | O5: At risk (u)
A6: 46276 | B6: Geelong | C6: 2 | D6: 5 | E6: Vespasian | F6: Bet | G6: Bet | H6: 6.3 | I6: 9.8 | J6: 0.0253 | K6: 1 | L6: 2 | M6: Loss | N6: =IF(M6="Win",IF(F6="Bet",(I6-1)*K6,K6),IF(M6="Loss",IF(F6="Bet",-K6,-(I6-1)*K6),IF(M6="Void",0,""))) | O6: =IF(OR(M6="Win",M6="Loss"),IF(F6="Bet",K6,(I6-1)*K6),"")
A7: 46276 | B7: Geelong | C7: 6 | D7: 10 | E7: Karren | F7: Lay | G7: Lay | H7: 2.85 | I7: 1.98 | J7: -0.1505 | K7: 1 | L7: 2 | M7: Win | N7: =IF(M7="Win",IF(F7="Bet",(I7-1)*K7,K7),IF(M7="Loss",IF(F7="Bet",-K7,-(I7-1)*K7),IF(M7="Void",0,""))) | O7: =IF(OR(M7="Win",M7="Loss"),IF(F7="Bet",K7,(I7-1)*K7),"")
A8: 46276 | B8: Bordertown | C8: 1 | D8: 6 | E8: Gradivus | F8: Lay | G8: Lay | H8: 4.9 | I8: 3.3 | J8: -0.1004 | K8: 1 | L8: 4 | M8: Win | N8: =IF(M8="Win",IF(F8="Bet",(I8-1)*K8,K8),IF(M8="Loss",IF(F8="Bet",-K8,-(I8-1)*K8),IF(M8="Void",0,""))) | O8: =IF(OR(M8="Win",M8="Loss"),IF(F8="Bet",K8,(I8-1)*K8),"")
A9: 46276 | B9: Bordertown | C9: 3 | D9: 6 | E9: Splash Of White | F9: Bet | G9: Bet | H9: 7.6 | I9: 9.5 | J9: 0.0258 | K9: 1 | L9: 6 | M9: Loss | N9: =IF(M9="Win",IF(F9="Bet",(I9-1)*K9,K9),IF(M9="Loss",IF(F9="Bet",-K9,-(I9-1)*K9),IF(M9="Void",0,""))) | O9: =IF(OR(M9="Win",M9="Loss"),IF(F9="Bet",K9,(I9-1)*K9),"")
A10: 46276 | B10: Tuncurry | C10: 3 | D10: 1 | E10: Sea Level | F10: Lay | G10: Lay | H10: 2.25 | I10: 1.75 | J10: -0.1224 | K10: 1 | L10: 1 | M10: Loss | N10: =IF(M10="Win",IF(F10="Bet",(I10-1)*K10,K10),IF(M10="Loss",IF(F10="Bet",-K10,-(I10-1)*K10),IF(M10="Void",0,""))) | O10: =IF(OR(M10="Win",M10="Loss"),IF(F10="Bet",K10,(I10-1)*K10),"")
A11: 46276 | B11: Tuncurry | C11: 7 | D11: 1 | E11: It's A Knockout | F11: Bet | G11: Bet | H11: 6.5 | I11: 8.5 | J11: 0.0354 | K11: 1 | L11: 5 | M11: Loss | N11: =IF(M11="Win",IF(F11="Bet",(I11-1)*K11,K11),IF(M11="Loss",IF(F11="Bet",-K11,-(I11-1)*K11),IF(M11="Void",0,""))) | O11: =IF(OR(M11="Win",M11="Loss"),IF(F11="Bet",K11,(I11-1)*K11),"")
A12: 46276 | B12: Tuncurry | C12: 8 | D12: 13 | E12: Andrea | F12: Lay | G12: Lay | H12: 2.35 | I12: 1.75 | J12: -0.144 | K12: 1 | L12: 1 | M12: Loss | N12: =IF(M12="Win",IF(F12="Bet",(I12-1)*K12,K12),IF(M12="Loss",IF(F12="Bet",-K12,-(I12-1)*K12),IF(M12="Void",0,""))) | O12: =IF(OR(M12="Win",M12="Loss"),IF(F12="Bet",K12,(I12-1)*K12),"")
A13: 46276 | B13: Goulburn | C13: 2 | D13: 6 | E13: Spain | F13: Lay | G13: Lay | H13: 1.65 | I13: 1.35 | J13: -0.1291 | K13: 1 | L13: 1 | M13: Loss | N13: =IF(M13="Win",IF(F13="Bet",(I13-1)*K13,K13),IF(M13="Loss",IF(F13="Bet",-K13,-(I13-1)*K13),IF(M13="Void",0,""))) | O13: =IF(OR(M13="Win",M13="Loss"),IF(F13="Bet",K13,(I13-1)*K13),"")
A14: 46276 | B14: Goulburn | C14: 3 | D14: 10 | E14: Montresor | F14: Lay | G14: Lay | H14: 2.4 | I14: 1.83 | J14: -0.1254 | K14: 1 | L14: 2 | M14: Win | N14: =IF(M14="Win",IF(F14="Bet",(I14-1)*K14,K14),IF(M14="Loss",IF(F14="Bet",-K14,-(I14-1)*K14),IF(M14="Void",0,""))) | O14: =IF(OR(M14="Win",M14="Loss"),IF(F14="Bet",K14,(I14-1)*K14),"")
A15: 46276 | B15: Sunshine Coast | C15: 1 | D15: 1 | E15: Sealord | F15: Bet | G15: Prime | H15: 3.3 | I15: 4.2 | J15: 0.0617 | K15: 1 | L15: 4 | M15: Loss | N15: =IF(M15="Win",IF(F15="Bet",(I15-1)*K15,K15),IF(M15="Loss",IF(F15="Bet",-K15,-(I15-1)*K15),IF(M15="Void",0,""))) | O15: =IF(OR(M15="Win",M15="Loss"),IF(F15="Bet",K15,(I15-1)*K15),"")
A16: 46276 | B16: Sunshine Coast | C16: 1 | D16: 5 | E16: Amelioration | F16: Lay | G16: Lay | H16: 3 | I16: 2.25 | J16: -0.1152 | K16: 1 | L16: 3 | M16: Win | N16: =IF(M16="Win",IF(F16="Bet",(I16-1)*K16,K16),IF(M16="Loss",IF(F16="Bet",-K16,-(I16-1)*K16),IF(M16="Void",0,""))) | O16: =IF(OR(M16="Win",M16="Loss"),IF(F16="Bet",K16,(I16-1)*K16),"")
A17: 46276 | B17: Sunshine Coast | C17: 8 | D17: 5 | E17: Brass Band | F17: Bet | G17: Bet | H17: 4.8 | I17: 6 | J17: 0.0432 | K17: 1 | L17: 3 | M17: Loss | N17: =IF(M17="Win",IF(F17="Bet",(I17-1)*K17,K17),IF(M17="Loss",IF(F17="Bet",-K17,-(I17-1)*K17),IF(M17="Void",0,""))) | O17: =IF(OR(M17="Win",M17="Loss"),IF(F17="Bet",K17,(I17-1)*K17),"")
... A66: 46277 | B66: Carnarvon | C66: 1 | D66: 1 | E66: Another Nephew | F66: Bet | G66: Bet | H66: 3.3 | I66: 4.06 | J66: 0.039 | K66: 1 | L66: 1 | M66: Win | N66: =IF(M66="Win",IF(F66="Bet",(I66-1)*K66,K66),IF(M66="Loss",IF(F66="Bet",-K66,-(I66-1)*K66),IF(M66="Void",0,""))) | O66: =IF(OR(M66="Win",M66="Loss"),IF(F66="Bet",K66,(I66-1)*K66),"")
A67: 46277 | B67: Toowoomba | C67: 1 | D67: 11 | E67: Crypto Miss | F67: Lay | G67: Lay | H67: 4.3 | I67: 2.8 | J67: -0.1219 | K67: 1 | L67: Unplaced | M67: Win | N67: =IF(M67="Win",IF(F67="Bet",(I67-1)*K67,K67),IF(M67="Loss",IF(F67="Bet",-K67,-(I67-1)*K67),IF(M67="Void",0,""))) | O67: =IF(OR(M67="Win",M67="Loss"),IF(F67="Bet",K67,(I67-1)*K67),"")
A68: 46277 | B68: Toowoomba | C68: 6 | D68: 8 | E68: Shrimpton | F68: Bet | G68: Bet | H68: 4.4 | I68: 5.4 | J68: 0.0291 | K68: 1 | L68: 1 | M68: Win | N68: =IF(M68="Win",IF(F68="Bet",(I68-1)*K68,K68),IF(M68="Loss",IF(F68="Bet",-K68,-(I68-1)*K68),IF(M68="Void",0,""))) | O68: =IF(OR(M68="Win",M68="Loss"),IF(F68="Bet",K68,(I68-1)*K68),"")
A69: 46277 | B69: Flemington | C69: 2 | D69: 5 | E69: Lara Antipova | F69: Bet | G69: Prime | H69: 6.4 | I69: 9.92 | J69: 0.0501 | K69: 1 | L69: 1 | M69: Win | N69: =IF(M69="Win",IF(F69="Bet",(I69-1)*K69,K69),IF(M69="Loss",IF(F69="Bet",-K69,-(I69-1)*K69),IF(M69="Void",0,""))) | O69: =IF(OR(M69="Win",M69="Loss"),IF(F69="Bet",K69,(I69-1)*K69),"")
A70: 46277 | B70: Mackay | C70: 2 | D70: 4 | E70: Elegant Venus | F70: Bet | G70: Bet | H70: 3 | I70: 3.46 | J70: 0.0257 | K70: 1 | L70: 1 | M70: Win | N70: =IF(M70="Win",IF(F70="Bet",(I70-1)*K70,K70),IF(M70="Loss",IF(F70="Bet",-K70,-(I70-1)*K70),IF(M70="Void",0,""))) | O70: =IF(OR(M70="Win",M70="Loss"),IF(F70="Bet",K70,(I70-1)*K70),"")
A71: 46277 | B71: Alice Springs | C71: 2 | D71: 2 | E71: Grinzinger Lass | F71: Bet | G71: Bet | H71: 4.2 | I71: 5.22 | J71: 0.0321 | K71: 1 | L71: 4 | M71: Loss | N71: =IF(M71="Win",IF(F71="Bet",(I71-1)*K71,K71),IF(M71="Loss",IF(F71="Bet",-K71,-(I71-1)*K71),IF(M71="Void",0,""))) | O71: =IF(OR(M71="Win",M71="Loss"),IF(F71="Bet",K71,(I71-1)*K71),"")
A72: 46278 | B72: Dalby | C72: 4 | D72: 6 | E72: Lady Willpower | F72: Lay | G72: Lay | H72: 1.45 | I72: 1.22 | J72: -0.1281 | K72: 1 | L72: 1 | M72: Loss | N72: =IF(M72="Win",IF(F72="Bet",(I72-1)*K72,K72),IF(M72="Loss",IF(F72="Bet",-K72,-(I72-1)*K72),IF(M72="Void",0,""))) | O72: =IF(OR(M72="Win",M72="Loss"),IF(F72="Bet",K72,(I72-1)*K72),"")
A73: 46278 | B73: Dalby | C73: 6 | D73: 4 | E73: Solo Hunter | F73: Lay | G73: Lay | H73: 1.7 | I73: 1.4 | J73: -0.1297 | K73: 1 | L73: 1 | M73: Loss | N73: =IF(M73="Win",IF(F73="Bet",(I73-1)*K73,K73),IF(M73="Loss",IF(F73="Bet",-K73,-(I73-1)*K73),IF(M73="Void",0,""))) | O73: =IF(OR(M73="Win",M73="Loss"),IF(F73="Bet",K73,(I73-1)*K73),"")
A74: 46278 | B74: Dalby | C74: 8 | D74: 8 | E74: Snugg | F74: Lay | G74: Lay | H74: 3.5 | I74: 2.6 | J74: -0.0974 | K74: 1 | L74: 3 | M74: Win | N74: =IF(M74="Win",IF(F74="Bet",(I74-1)*K74,K74),IF(M74="Loss",IF(F74="Bet",-K74,-(I74-1)*K74),IF(M74="Void",0,""))) | O74: =IF(OR(M74="Win",M74="Loss"),IF(F74="Bet",K74,(I74-1)*K74),"")
A75: 46278 | B75: Sale | C75: 1 | D75: 4 | E75: Mr Margolin | F75: Lay | G75: Lay | H75: 5.8 | I75: 3.7 | J75: -0.0966 | K75: 1 | L75: 1 | M75: Loss | N75: =IF(M75="Win",IF(F75="Bet",(I75-1)*K75,K75),IF(M75="Loss",IF(F75="Bet",-K75,-(I75-1)*K75),IF(M75="Void",0,""))) | O75: =IF(OR(M75="Win",M75="Loss"),IF(F75="Bet",K75,(I75-1)*K75),"")
A76: 46278 | B76: Sale | C76: 3 | D76: 12 | E76: Zendarina | F76: Lay | G76: Lay | H76: 3.7 | I76: 2.7 | J76: -0.0974 | K76: 1 | L76: 1 | M76: Loss | N76: =IF(M76="Win",IF(F76="Bet",(I76-1)*K76,K76),IF(M76="Loss",IF(F76="Bet",-K76,-(I76-1)*K76),IF(M76="Void",0,""))) | O76: =IF(OR(M76="Win",M76="Loss"),IF(F76="Bet",K76,(I76-1)*K76),"")
A77: 46278 | B77: Sale | C77: 4 | D77: 12 | E77: Classic Secret | F77: Lay | G77: Lay | H77: 3.5 | I77: 2.75 | J77: -0.0759 | K77: 1 | L77: 10 | M77: Win | N77: =IF(M77="Win",IF(F77="Bet",(I77-1)*K77,K77),IF(M77="Loss",IF(F77="Bet",-K77,-(I77-1)*K77),IF(M77="Void",0,""))) | O77: =IF(OR(M77="Win",M77="Loss"),IF(F77="Bet",K77,(I77-1)*K77),"")
A78: 46278 | B78: Sale | C78: 6 | D78: 4 | E78: Exfortythree | F78: Bet | G78: Bet | H78: 4.3 | I78: 5 | J78: 0.0351 | K78: 1 | L78: 5 | M78: Loss | N78: =IF(M78="Win",IF(F78="Bet",(I78-1)*K78,K78),IF(M78="Loss",IF(F78="Bet",-K78,-(I78-1)*K78),IF(M78="Void",0,""))) | O78: =IF(OR(M78="Win",M78="Loss"),IF(F78="Bet",K78,(I78-1)*K78),"")
A79: 46278 | B79: Coffs Harbour | C79: 3 | D79: 10 | E79: Magic Snitzel | F79: Lay | G79: Lay | H79: 3.1 | I79: 2.26 | J79: -0.0605 | K79: 1 | L79: 4 | M79: Win | N79: =IF(M79="Win",IF(F79="Bet",(I79-1)*K79,K79),IF(M79="Loss",IF(F79="Bet",-K79,-(I79-1)*K79),IF(M79="Void",0,""))) | O79: =IF(OR(M79="Win",M79="Loss"),IF(F79="Bet",K79,(I79-1)*K79),"")
... A89: 46278 | B89: Northam | C89: 1 | D89: 1 | E89: Who's Bent | F89: Bet | G89: Bet | H89: 3.5 | I89: 4.2 | J89: 0.0477 | K89: 1 | L89: 1 | M89: Win | N89: =IF(M89="Win",IF(F89="Bet",(I89-1)*K89,K89),IF(M89="Loss",IF(F89="Bet",-K89,-(I89-1)*K89),IF(M89="Void",0,""))) | O89: =IF(OR(M89="Win",M89="Loss"),IF(F89="Bet",K89,(I89-1)*K89),"")
A90: 46278 | B90: Bathurst | C90: 7 | D90: 2 | E90: Fearn Trick | F90: Bet | G90: Bet | H90: 7.5 | I90: 9.5 | J90: 0.0279 | K90: 1 | M90: Void | N90: =IF(M90="Win",IF(F90="Bet",(I90-1)*K90,K90),IF(M90="Loss",IF(F90="Bet",-K90,-(I90-1)*K90),IF(M90="Void",0,""))) | O90: =IF(OR(M90="Win",M90="Loss"),IF(F90="Bet",K90,(I90-1)*K90),"")
A91: 46278 | B91: Dalby | C91: 3 | D91: 4 | E91: Royal Diplomat | F91: Lay | G91: Lay | H91: 2.35 | I91: 2.05 | J91: -0.0632 | K91: 1 | L91: 1 | M91: Loss | N91: =IF(M91="Win",IF(F91="Bet",(I91-1)*K91,K91),IF(M91="Loss",IF(F91="Bet",-K91,-(I91-1)*K91),IF(M91="Void",0,""))) | O91: =IF(OR(M91="Win",M91="Loss"),IF(F91="Bet",K91,(I91-1)*K91),"")
A92: 46278 | B92: Sale | C92: 5 | D92: 10 | E92: Rhyme Dust | F92: Lay | G92: Lay | H92: 5.2 | I92: 3.7 | J92: -0.0787 | K92: 1 | L92: 9 | M92: Win | N92: =IF(M92="Win",IF(F92="Bet",(I92-1)*K92,K92),IF(M92="Loss",IF(F92="Bet",-K92,-(I92-1)*K92),IF(M92="Void",0,""))) | O92: =IF(OR(M92="Win",M92="Loss"),IF(F92="Bet",K92,(I92-1)*K92),"")
A93: 46279 | B93: Hamilton | C93: 3 | D93: 1 | E93: Asal | F93: Lay | G93: Lay | H93: 2.65 | I93: 2.1 | J93: -0.1008 | K93: 1 | L93: 1 | M93: Loss | N93: =IF(M93="Win",IF(F93="Bet",(I93-1)*K93,K93),IF(M93="Loss",IF(F93="Bet",-K93,-(I93-1)*K93),IF(M93="Void",0,""))) | O93: =IF(OR(M93="Win",M93="Loss"),IF(F93="Bet",K93,(I93-1)*K93),"")
A94: 46279 | B94: Hamilton | C94: 8 | D94: 6 | E94: Share The Stars | F94: Lay | G94: Lay | H94: 5.6 | I94: 3.5 | J94: -0.1079 | K94: 1 | L94: 8 | M94: Win | N94: =IF(M94="Win",IF(F94="Bet",(I94-1)*K94,K94),IF(M94="Loss",IF(F94="Bet",-K94,-(I94-1)*K94),IF(M94="Void",0,""))) | O94: =IF(OR(M94="Win",M94="Loss"),IF(F94="Bet",K94,(I94-1)*K94),"")
A95: 46279 | B95: Tamworth | C95: 1 | D95: 4 | E95: Heapy's Legacy | F95: Lay | G95: Lay | H95: 3.2 | I95: 2.4 | J95: -0.1061 | K95: 1 | L95: 3 | M95: Win | N95: =IF(M95="Win",IF(F95="Bet",(I95-1)*K95,K95),IF(M95="Loss",IF(F95="Bet",-K95,-(I95-1)*K95),IF(M95="Void",0,""))) | O95: =IF(OR(M95="Win",M95="Loss"),IF(F95="Bet",K95,(I95-1)*K95),"")
A96: 46279 | B96: Tamworth | C96: 2 | D96: 4 | E96: Sammaan City | F96: Lay | G96: Lay | H96: 2.05 | I96: 1.7 | J96: -0.1013 | K96: 1 | L96: 6 | M96: Win | N96: =IF(M96="Win",IF(F96="Bet",(I96-1)*K96,K96),IF(M96="Loss",IF(F96="Bet",-K96,-(I96-1)*K96),IF(M96="Void",0,""))) | O96: =IF(OR(M96="Win",M96="Loss"),IF(F96="Bet",K96,(I96-1)*K96),"")
A97: 46279 | B97: Tamworth | C97: 4 | D97: 2 | E97: Mongolian Master | F97: Bet | G97: Bet | H97: 6.9 | I97: 9.6 | J97: 0.0335 | K97: 1 | L97: 3 | M97: Loss | N97: =IF(M97="Win",IF(F97="Bet",(I97-1)*K97,K97),IF(M97="Loss",IF(F97="Bet",-K97,-(I97-1)*K97),IF(M97="Void",0,""))) | O97: =IF(OR(M97="Win",M97="Loss"),IF(F97="Bet",K97,(I97-1)*K97),"")
A98: 46279 | B98: Tamworth | C98: 5 | D98: 1 | E98: Dunquin | F98: Lay | G98: Lay | H98: 3.3 | I98: 2.2 | J98: -0.1514 | K98: 1 | L98: 2 | M98: Win | N98: =IF(M98="Win",IF(F98="Bet",(I98-1)*K98,K98),IF(M98="Loss",IF(F98="Bet",-K98,-(I98-1)*K98),IF(M98="Void",0,""))) | O98: =IF(OR(M98="Win",M98="Loss"),IF(F98="Bet",K98,(I98-1)*K98),"")
A99: 46279 | B99: Tamworth | C99: 6 | D99: 2 | E99: He's My Warrior | F99: Bet | G99: Bet | H99: 6.5 | I99: 8 | J99: 0.0286 | K99: 1 | L99: 6 | M99: Loss | N99: =IF(M99="Win",IF(F99="Bet",(I99-1)*K99,K99),IF(M99="Loss",IF(F99="Bet",-K99,-(I99-1)*K99),IF(M99="Void",0,""))) | O99: =IF(OR(M99="Win",M99="Loss"),IF(F99="Bet",K99,(I99-1)*K99),"")
A100: 46279 | B100: Tamworth | C100: 6 | D100: 5 | E100: Sipping Shamus | F100: Lay | G100: Lay | H100: 6.3 | I100: 3.8 | J100: -0.1049 | K100: 1 | L100: 5 | M100: Win | N100: =IF(M100="Win",IF(F100="Bet",(I100-1)*K100,K100),IF(M100="Loss",IF(F100="Bet",-K100,-(I100-1)*K100),IF(M100="Void",0,""))) | O100: =IF(OR(M100="Win",M100="Loss"),IF(F100="Bet",K100,(I100-1)*K100),"")
A101: 46279 | B101: Corowa | C101: 5 | D101: 11 | E101: Levens Hall | F101: Lay | G101: Lay | H101: 2.4 | I101: 1.9 | J101: -0.1072 | K101: 1 | L101: 2 | M101: Win | N101: =IF(M101="Win",IF(F101="Bet",(I101-1)*K101,K101),IF(M101="Loss",IF(F101="Bet",-K101,-(I101-1)*K101),IF(M101="Void",0,""))) | O101: =IF(OR(M101="Win",M101="Loss"),IF(F101="Bet",K101,(I101-1)*K101),"")
A102: 46279 | B102: Corowa | C102: 6 | D102: 3 | E102: Chief Of War | F102: Lay | G102: Lay | H102: 2.15 | I102: 1.65 | J102: -0.1403 | K102: 1 | L102: 2 | M102: Win | N102: =IF(M102="Win",IF(F102="Bet",(I102-1)*K102,K102),IF(M102="Loss",IF(F102="Bet",-K102,-(I102-1)*K102),IF(M102="Void",0,""))) | O102: =IF(OR(M102="Win",M102="Loss"),IF(F102="Bet",K102,(I102-1)*K102),"")
... A144: 46281 | B144: Belmont | C144: 7 | D144: 5 | E144: Vampi Queen | F144: Lay | G144: Lay | H144: 6 | I144: 2.5 | J144: -0.1913 | K144: 1 | L144: 1 | M144: Loss | N144: =IF(M144="Win",IF(F144="Bet",(I144-1)*K144,K144),IF(M144="Loss",IF(F144="Bet",-K144,-(I144-1)*K144),IF(M144="Void",0,""))) | O144: =IF(OR(M144="Win",M144="Loss"),IF(F144="Bet",K144,(I144-1)*K144),"")
A145: 46281 | B145: Caulfield Heath | C145: 2 | D145: 2 | E145: Lake Vostok | F145: Bet | G145: Bet | H145: 5.6 | I145: 7 | J145: 0.0355 | K145: 1 | M145: Void | N145: =IF(M145="Win",IF(F145="Bet",(I145-1)*K145,K145),IF(M145="Loss",IF(F145="Bet",-K145,-(I145-1)*K145),IF(M145="Void",0,""))) | O145: =IF(OR(M145="Win",M145="Loss"),IF(F145="Bet",K145,(I145-1)*K145),"")
A146: 46281 | B146: Canterbury | C146: 4 | D146: 8 | E146: Ertijaaj | F146: Lay | G146: Lay | H146: 10.4 | I146: 4.2 | J146: -0.1417 | K146: 1 | M146: Void | N146: =IF(M146="Win",IF(F146="Bet",(I146-1)*K146,K146),IF(M146="Loss",IF(F146="Bet",-K146,-(I146-1)*K146),IF(M146="Void",0,""))) | O146: =IF(OR(M146="Win",M146="Loss"),IF(F146="Bet",K146,(I146-1)*K146),"")
A147: 46281 | B147: Caulfield Heath | C147: 1 | D147: 1 | E147: Corviglia | F147: Bet | G147: Prime | H147: 5.3 | I147: 9.36 | J147: 0.065 | K147: 1 | L147: 2 | M147: Loss | N147: =IF(M147="Win",IF(F147="Bet",(I147-1)*K147,K147),IF(M147="Loss",IF(F147="Bet",-K147,-(I147-1)*K147),IF(M147="Void",0,""))) | O147: =IF(OR(M147="Win",M147="Loss"),IF(F147="Bet",K147,(I147-1)*K147),"")
A148: 46281 | B148: Launceston | C148: 6 | D148: 3 | E148: Vinraam | F148: Lay | G148: Lay | H148: 7.1 | I148: 3.4 | J148: -0.1535 | K148: 1 | L148: 5 | M148: Win | N148: =IF(M148="Win",IF(F148="Bet",(I148-1)*K148,K148),IF(M148="Loss",IF(F148="Bet",-K148,-(I148-1)*K148),IF(M148="Void",0,""))) | O148: =IF(OR(M148="Win",M148="Loss"),IF(F148="Bet",K148,(I148-1)*K148),"")
A149: 46281 | B149: Balaklava | C149: 1 | D149: 1 | E149: Sidebar | F149: Bet | G149: Bet | H149: 5.9 | I149: 10.5 | J149: 0.0262 | K149: 1 | L149: 4 | M149: Loss | N149: =IF(M149="Win",IF(F149="Bet",(I149-1)*K149,K149),IF(M149="Loss",IF(F149="Bet",-K149,-(I149-1)*K149),IF(M149="Void",0,""))) | O149: =IF(OR(M149="Win",M149="Loss"),IF(F149="Bet",K149,(I149-1)*K149),"")
A150: 46281 | B150: Doomben | C150: 3 | D150: 9 | E150: Flaressence | F150: Bet | G150: Bet | H150: 3.9 | I150: 6 | J150: 0.0388 | K150: 1 | L150: 2 | M150: Loss | N150: =IF(M150="Win",IF(F150="Bet",(I150-1)*K150,K150),IF(M150="Loss",IF(F150="Bet",-K150,-(I150-1)*K150),IF(M150="Void",0,""))) | O150: =IF(OR(M150="Win",M150="Loss"),IF(F150="Bet",K150,(I150-1)*K150),"")
A151: 46281 | B151: Caulfield Heath | C151: 7 | D151: 4 | E151: Rhapsody Chic | F151: Bet | G151: Bet | H151: 11.7 | I151: 31 | J151: 0.0264 | K151: 1 | L151: 8 | M151: Loss | N151: =IF(M151="Win",IF(F151="Bet",(I151-1)*K151,K151),IF(M151="Loss",IF(F151="Bet",-K151,-(I151-1)*K151),IF(M151="Void",0,""))) | O151: =IF(OR(M151="Win",M151="Loss"),IF(F151="Bet",K151,(I151-1)*K151),"")
A152: 46281 | B152: Launceston | C152: 6 | D152: 2 | E152: Bailed | F152: Lay | G152: Lay | H152: 5.5 | I152: 2.6 | J152: -0.1627 | K152: 1 | L152: 3 | M152: Win | N152: =IF(M152="Win",IF(F152="Bet",(I152-1)*K152,K152),IF(M152="Loss",IF(F152="Bet",-K152,-(I152-1)*K152),IF(M152="Void",0,""))) | O152: =IF(OR(M152="Win",M152="Loss"),IF(F152="Bet",K152,(I152-1)*K152),"")
A153: 46281 | B153: Canterbury | C153: 5 | D153: 1 | E153: Tremonti | F153: Bet | G153: Bet | H153: 9.1 | I153: 21 | J153: 0.0426 | K153: 1 | L153: 10 | M153: Loss | N153: =IF(M153="Win",IF(F153="Bet",(I153-1)*K153,K153),IF(M153="Loss",IF(F153="Bet",-K153,-(I153-1)*K153),IF(M153="Void",0,""))) | O153: =IF(OR(M153="Win",M153="Loss"),IF(F153="Bet",K153,(I153-1)*K153),"")
A154: 46281 | B154: Balaklava | C154: 8 | D154: 8 | E154: Embellisher | F154: Lay | G154: Lay | H154: 7.3 | I154: 3.1 | J154: -0.1494 | K154: 1 | L154: 4 | M154: Win | N154: =IF(M154="Win",IF(F154="Bet",(I154-1)*K154,K154),IF(M154="Loss",IF(F154="Bet",-K154,-(I154-1)*K154),IF(M154="Void",0,""))) | O154: =IF(OR(M154="Win",M154="Loss"),IF(F154="Bet",K154,(I154-1)*K154),"")
A155: 46281 | B155: Belmont | C155: 6 | D155: 7 | E155: Streamlined | F155: Lay | G155: Lay | H155: 3.1 | I155: 2.25 | J155: -0.1047 | K155: 1 | L155: 1 | M155: Loss | N155: =IF(M155="Win",IF(F155="Bet",(I155-1)*K155,K155),IF(M155="Loss",IF(F155="Bet",-K155,-(I155-1)*K155),IF(M155="Void",0,""))) | O155: =IF(OR(M155="Win",M155="Loss"),IF(F155="Bet",K155,(I155-1)*K155),"")
A156: 46281 | B156: Doomben | C156: 5 | D156: 1 | E156: Global Eclipse | F156: Lay | G156: Lay | H156: 4 | I156: 2.9 | J156: -0.1072 | K156: 1 | L156: 1 | M156: Loss | N156: =IF(M156="Win",IF(F156="Bet",(I156-1)*K156,K156),IF(M156="Loss",IF(F156="Bet",-K156,-(I156-1)*K156),IF(M156="Void",0,""))) | O156: =IF(OR(M156="Win",M156="Loss"),IF(F156="Bet",K156,(I156-1)*K156),"")
A157: 46281 | B157: Doomben | C157: 6 | D157: 4 | E157: Lockyer | F157: Lay | G157: Lay | H157: 3.1 | I157: 2.25 | J157: -0.107 | K157: 1 | L157: 1 | M157: Loss | N157: =IF(M157="Win",IF(F157="Bet",(I157-1)*K157,K157),IF(M157="Loss",IF(F157="Bet",-K157,-(I157-1)*K157),IF(M157="Void",0,""))) | O157: =IF(OR(M157="Win",M157="Loss"),IF(F157="Bet",K157,(I157-1)*K157),"")
A158: 46281 | B158: Balaklava | C158: 8 | D158: 1 | E158: Super Lad | F158: Bet | G158: Bet | H158: 5.2 | I158: 6 | J158: 0.0257 | K158: 1 | L158: 5 | M158: Loss | N158: =IF(M158="Win",IF(F158="Bet",(I158-1)*K158,K158),IF(M158="Loss",IF(F158="Bet",-K158,-(I158-1)*K158),IF(M158="Void",0,""))) | O158: =IF(OR(M158="Win",M158="Loss"),IF(F158="Bet",K158,(I158-1)*K158),"")
... A169: 46282 | B169: Beaudesert | C169: 1 | D169: 8 | E169: Wasai | F169: Lay | G169: Lay | H169: 2.35 | I169: 1.75 | J169: -0.1418 | K169: 1 | L169: 3 | M169: Win | N169: =IF(M169="Win",IF(F169="Bet",(I169-1)*K169,K169),IF(M169="Loss",IF(F169="Bet",-K169,-(I169-1)*K169),IF(M169="Void",0,""))) | O169: =IF(OR(M169="Win",M169="Loss"),IF(F169="Bet",K169,(I169-1)*K169),"")
A170: 46282 | B170: Mornington | C170: 7 | D170: 8 | E170: Justique | F170: Lay | G170: Lay | H170: 7.6 | I170: 4.2 | J170: -0.1063 | K170: 1 | M170: Void | N170: =IF(M170="Win",IF(F170="Bet",(I170-1)*K170,K170),IF(M170="Loss",IF(F170="Bet",-K170,-(I170-1)*K170),IF(M170="Void",0,""))) | O170: =IF(OR(M170="Win",M170="Loss"),IF(F170="Bet",K170,(I170-1)*K170),"")
A171: 46282 | B171: Mornington | C171: 1 | D171: 11 | E171: Adakite | F171: Lay | G171: Lay | H171: 3.4 | I171: 2.15 | J171: -0.122 | K171: 1 | L171: 2 | M171: Win | N171: =IF(M171="Win",IF(F171="Bet",(I171-1)*K171,K171),IF(M171="Loss",IF(F171="Bet",-K171,-(I171-1)*K171),IF(M171="Void",0,""))) | O171: =IF(OR(M171="Win",M171="Loss"),IF(F171="Bet",K171,(I171-1)*K171),"")
A172: 46282 | B172: Beaudesert | C172: 9 | D172: 7 | E172: Ed I Am | F172: Lay | G172: Lay | H172: 3.2 | I172: 2.07 | J172: -0.0618 | K172: 1 | L172: 1 | M172: Loss | N172: =IF(M172="Win",IF(F172="Bet",(I172-1)*K172,K172),IF(M172="Loss",IF(F172="Bet",-K172,-(I172-1)*K172),IF(M172="Void",0,""))) | O172: =IF(OR(M172="Win",M172="Loss"),IF(F172="Bet",K172,(I172-1)*K172),"")
A173: 46282 | B173: Bunbury | C173: 7 | D173: 4 | E173: Bondi Star | F173: Lay | G173: Lay | H173: 4.7 | I173: 3.4 | J173: -0.0651 | K173: 1 | L173: 3 | M173: Win | N173: =IF(M173="Win",IF(F173="Bet",(I173-1)*K173,K173),IF(M173="Loss",IF(F173="Bet",-K173,-(I173-1)*K173),IF(M173="Void",0,""))) | O173: =IF(OR(M173="Win",M173="Loss"),IF(F173="Bet",K173,(I173-1)*K173),"")
A174: 46282 | B174: Bunbury | C174: 8 | D174: 10 | E174: Looks | F174: Lay | G174: Lay | H174: 6.8 | I174: 4.6 | J174: -0.0696 | K174: 1 | L174: 8 | M174: Win | N174: =IF(M174="Win",IF(F174="Bet",(I174-1)*K174,K174),IF(M174="Loss",IF(F174="Bet",-K174,-(I174-1)*K174),IF(M174="Void",0,""))) | O174: =IF(OR(M174="Win",M174="Loss"),IF(F174="Bet",K174,(I174-1)*K174),"")
A175: 46283 | B175: Canberra | C175: 2 | D175: 2 | E175: Inna Zou | F175: Lay | G175: Lay | H175: 5.5 | I175: 3.3 | J175: -0.074 | K175: 1 | L175: 2 | M175: Win | N175: =IF(M175="Win",IF(F175="Bet",(I175-1)*K175,K175),IF(M175="Loss",IF(F175="Bet",-K175,-(I175-1)*K175),IF(M175="Void",0,""))) | O175: =IF(OR(M175="Win",M175="Loss"),IF(F175="Bet",K175,(I175-1)*K175),"")
A176: 46283 | B176: Newcastle | C176: 7 | D176: 12 | E176: Mr Miller | F176: Lay | G176: Lay | H176: 3.5 | I176: 1.68 | J176: -0.105 | K176: 1 | L176: 3 | M176: Win | N176: =IF(M176="Win",IF(F176="Bet",(I176-1)*K176,K176),IF(M176="Loss",IF(F176="Bet",-K176,-(I176-1)*K176),IF(M176="Void",0,""))) | O176: =IF(OR(M176="Win",M176="Loss"),IF(F176="Bet",K176,(I176-1)*K176),"")
A177: 46283 | B177: Ballarat | C177: 1 | D177: 5 | E177: Aryaam | F177: Lay | G177: Lay | H177: 4 | I177: 3.2 | J177: -0.0604 | K177: 1 | M177: Void | N177: =IF(M177="Win",IF(F177="Bet",(I177-1)*K177,K177),IF(M177="Loss",IF(F177="Bet",-K177,-(I177-1)*K177),IF(M177="Void",0,""))) | O177: =IF(OR(M177="Win",M177="Loss"),IF(F177="Bet",K177,(I177-1)*K177),"")
A178: 46283 | B178: Canberra | C178: 6 | D178: 11 | E178: Hello G'day | F178: Lay | G178: Lay | H178: 3.1 | I178: 1.47 | J178: -0.0745 | K178: 1 | L178: 3 | M178: Win | N178: =IF(M178="Win",IF(F178="Bet",(I178-1)*K178,K178),IF(M178="Loss",IF(F178="Bet",-K178,-(I178-1)*K178),IF(M178="Void",0,""))) | O178: =IF(OR(M178="Win",M178="Loss"),IF(F178="Bet",K178,(I178-1)*K178),"")
A179: 46283 | B179: Canberra | C179: 7 | D179: 2 | E179: Vella's Best | F179: Lay | G179: Lay | H179: 4.1 | I179: 2.76 | J179: -0.0614 | K179: 1 | L179: 11 | M179: Win | N179: =IF(M179="Win",IF(F179="Bet",(I179-1)*K179,K179),IF(M179="Loss",IF(F179="Bet",-K179,-(I179-1)*K179),IF(M179="Void",0,""))) | O179: =IF(OR(M179="Win",M179="Loss"),IF(F179="Bet",K179,(I179-1)*K179),"")
A180: 46283 | B180: Canberra | C180: 8 | D180: 10 | E180: Judith's Revenge | F180: Lay | G180: Lay | H180: 2 | I180: 1.75 | J180: -0.0701 | K180: 1 | L180: 4 | M180: Win | N180: =IF(M180="Win",IF(F180="Bet",(I180-1)*K180,K180),IF(M180="Loss",IF(F180="Bet",-K180,-(I180-1)*K180),IF(M180="Void",0,""))) | O180: =IF(OR(M180="Win",M180="Loss"),IF(F180="Bet",K180,(I180-1)*K180),"")
A181: 46283 | B181: Canberra | C181: 3 | D181: 2 | E181: Feazabeel | F181: Lay | G181: Lay | H181: 2.3 | I181: 1.78 | J181: -0.0645 | K181: 1 | L181: 1 | M181: Loss | N181: =IF(M181="Win",IF(F181="Bet",(I181-1)*K181,K181),IF(M181="Loss",IF(F181="Bet",-K181,-(I181-1)*K181),IF(M181="Void",0,""))) | O181: =IF(OR(M181="Win",M181="Loss"),IF(F181="Bet",K181,(I181-1)*K181),"")
A182: 46283 | B182: Newcastle | C182: 1 | D182: 4 | E182: Tacitly | F182: Lay | G182: Lay | H182: 5.1 | I182: 3.7 | J182: -0.0759 | K182: 1 | L182: 2 | M182: Win | N182: =IF(M182="Win",IF(F182="Bet",(I182-1)*K182,K182),IF(M182="Loss",IF(F182="Bet",-K182,-(I182-1)*K182),IF(M182="Void",0,""))) | O182: =IF(OR(M182="Win",M182="Loss"),IF(F182="Bet",K182,(I182-1)*K182),"")
A183: 46283 | B183: Canberra | C183: 1 | D183: 1 | E183: Liyah's Girl | F183: Lay | G183: Lay | H183: 3.6 | I183: 2.74 | J183: -0.0855 | K183: 1 | L183: 2 | M183: Win | N183: =IF(M183="Win",IF(F183="Bet",(I183-1)*K183,K183),IF(M183="Loss",IF(F183="Bet",-K183,-(I183-1)*K183),IF(M183="Void",0,""))) | O183: =IF(OR(M183="Win",M183="Loss"),IF(F183="Bet",K183,(I183-1)*K183),"")
A184: 46283 | B184: Canberra | C184: 1 | D184: 2 | E184: Unmatched | F184: Bet | G184: Prime | H184: 5.2 | I184: 9.64 | J184: 0.027 | K184: 1 | L184: 3 | M184: Loss | N184: =IF(M184="Win",IF(F184="Bet",(I184-1)*K184,K184),IF(M184="Loss",IF(F184="Bet",-K184,-(I184-1)*K184),IF(M184="Void",0,""))) | O184: =IF(OR(M184="Win",M184="Loss"),IF(F184="Bet",K184,(I184-1)*K184),"")
A185: 46283 | B185: Townsville | C185: 8 | D185: 4 | E185: Metalcraft | F185: Lay | G185: Lay | H185: 8.5 | I185: 1.6 | J185: -0.4085 | K185: 1 | L185: 1 | M185: Loss | N185: =IF(M185="Win",IF(F185="Bet",(I185-1)*K185,K185),IF(M185="Loss",IF(F185="Bet",-K185,-(I185-1)*K185),IF(M185="Void",0,""))) | O185: =IF(OR(M185="Win",M185="Loss"),IF(F185="Bet",K185,(I185-1)*K185),"")
A186: 46283 | B186: Canberra | C186: 5 | D186: 3 | E186: Shaft Attack | F186: Bet | G186: Bet | H186: 6.3 | I186: 7.5 | J186: 0.0255 | K186: 1 | L186: 2 | M186: Loss | N186: =IF(M186="Win",IF(F186="Bet",(I186-1)*K186,K186),IF(M186="Loss",IF(F186="Bet",-K186,-(I186-1)*K186),IF(M186="Void",0,""))) | O186: =IF(OR(M186="Win",M186="Loss"),IF(F186="Bet",K186,(I186-1)*K186),"")
A187: 46283 | B187: Townsville | C187: 8 | D187: 2 | E187: New Hampshire | F187: Bet | G187: Bet | H187: 11.3 | I187: 81 | J187: 0.0499 | K187: 1 | L187: 8 | M187: Loss | N187: =IF(M187="Win",IF(F187="Bet",(I187-1)*K187,K187),IF(M187="Loss",IF(F187="Bet",-K187,-(I187-1)*K187),IF(M187="Void",0,""))) | O187: =IF(OR(M187="Win",M187="Loss"),IF(F187="Bet",K187,(I187-1)*K187),"")
A188: 46283 | B188: Townsville | C188: 8 | D188: 11 | E188: Singular | F188: Bet | G188: Bet | H188: 9.2 | I188: 23 | J188: 0.0537 | K188: 1 | L188: 7 | M188: Loss | N188: =IF(M188="Win",IF(F188="Bet",(I188-1)*K188,K188),IF(M188="Loss",IF(F188="Bet",-K188,-(I188-1)*K188),IF(M188="Void",0,""))) | O188: =IF(OR(M188="Win",M188="Loss"),IF(F188="Bet",K188,(I188-1)*K188),"")
A189: 46283 | B189: Townsville | C189: 5 | D189: 8 | E189: Red Feathers | F189: Lay | G189: Lay | H189: 4.1 | I189: 1.95 | J189: -0.0908 | K189: 1 | L189: 10 | M189: Win | N189: =IF(M189="Win",IF(F189="Bet",(I189-1)*K189,K189),IF(M189="Loss",IF(F189="Bet",-K189,-(I189-1)*K189),IF(M189="Void",0,""))) | O189: =IF(OR(M189="Win",M189="Loss"),IF(F189="Bet",K189,(I189-1)*K189),"")
... A239: 46284 | B239: Belmont | C239: 4 | D239: 1 | E239: Too Dardy | F239: Bet | G239: Bet | H239: 4.7 | I239: 5.5 | J239: 0.0317 | K239: 1 | L239: 2 | M239: Loss | N239: =IF(M239="Win",IF(F239="Bet",(I239-1)*K239,K239),IF(M239="Loss",IF(F239="Bet",-K239,-(I239-1)*K239),IF(M239="Void",0,""))) | O239: =IF(OR(M239="Win",M239="Loss"),IF(F239="Bet",K239,(I239-1)*K239),"")
A240: 46284 | B240: Gold Coast | C240: 3 | D240: 11 | E240: Brain Wave | F240: Bet | G240: Bet | H240: 8.7 | I240: 12 | J240: 0.0318 | K240: 1 | M240: Void | N240: =IF(M240="Win",IF(F240="Bet",(I240-1)*K240,K240),IF(M240="Loss",IF(F240="Bet",-K240,-(I240-1)*K240),IF(M240="Void",0,""))) | O240: =IF(OR(M240="Win",M240="Loss"),IF(F240="Bet",K240,(I240-1)*K240),"")
A241: 46284 | B241: Eagle Farm | C241: 5 | D241: 6 | E241: Esha | F241: Lay | G241: Lay | H241: 2.1 | I241: 1.57 | J241: -0.0778 | K241: 1 | L241: 1 | M241: Loss | N241: =IF(M241="Win",IF(F241="Bet",(I241-1)*K241,K241),IF(M241="Loss",IF(F241="Bet",-K241,-(I241-1)*K241),IF(M241="Void",0,""))) | O241: =IF(OR(M241="Win",M241="Loss"),IF(F241="Bet",K241,(I241-1)*K241),"")
A242: 46284 | B242: Eagle Farm | C242: 6 | D242: 1 | E242: Midnight Spirit | F242: Bet | G242: Bet | H242: 8.1 | I242: 11 | J242: 0.0325 | K242: 1 | L242: 3 | M242: Loss | N242: =IF(M242="Win",IF(F242="Bet",(I242-1)*K242,K242),IF(M242="Loss",IF(F242="Bet",-K242,-(I242-1)*K242),IF(M242="Void",0,""))) | O242: =IF(OR(M242="Win",M242="Loss"),IF(F242="Bet",K242,(I242-1)*K242),"")
A243: 46284 | B243: Eagle Farm | C243: 6 | D243: 11 | E243: Miss Funny Honey | F243: Bet | G243: Bet | H243: 11.7 | I243: 16 | J243: 0.0231 | K243: 1 | M243: Void | N243: =IF(M243="Win",IF(F243="Bet",(I243-1)*K243,K243),IF(M243="Loss",IF(F243="Bet",-K243,-(I243-1)*K243),IF(M243="Void",0,""))) | O243: =IF(OR(M243="Win",M243="Loss"),IF(F243="Bet",K243,(I243-1)*K243),"")
A244: 46284 | B244: Eagle Farm | C244: 8 | D244: 12 | E244: Vincley | F244: Lay | G244: Lay | H244: 5.2 | I244: 3.8 | J244: -0.0695 | K244: 1 | M244: Void | N244: =IF(M244="Win",IF(F244="Bet",(I244-1)*K244,K244),IF(M244="Loss",IF(F244="Bet",-K244,-(I244-1)*K244),IF(M244="Void",0,""))) | O244: =IF(OR(M244="Win",M244="Loss"),IF(F244="Bet",K244,(I244-1)*K244),"")
A245: 46284 | B245: Newcastle | C245: 1 | D245: 8 | E245: Excelluna | F245: Lay | G245: Lay | H245: 3.2 | I245: 2.6 | J245: -0.0697 | K245: 1 | L245: 1 | M245: Loss | N245: =IF(M245="Win",IF(F245="Bet",(I245-1)*K245,K245),IF(M245="Loss",IF(F245="Bet",-K245,-(I245-1)*K245),IF(M245="Void",0,""))) | O245: =IF(OR(M245="Win",M245="Loss"),IF(F245="Bet",K245,(I245-1)*K245),"")
A246: 46284 | B246: Newcastle | C246: 2 | D246: 7 | E246: Klocke | F246: Lay | G246: Lay | H246: 2.05 | I246: 1.41 | J246: -0.0675 | K246: 1 | L246: 2 | M246: Win | N246: =IF(M246="Win",IF(F246="Bet",(I246-1)*K246,K246),IF(M246="Loss",IF(F246="Bet",-K246,-(I246-1)*K246),IF(M246="Void",0,""))) | O246: =IF(OR(M246="Win",M246="Loss"),IF(F246="Bet",K246,(I246-1)*K246),"")
A247: 46284 | B247: Gold Coast | C247: 7 | D247: 1 | E247: Grand Impact | F247: Lay | G247: Lay | H247: 3.3 | I247: 2.48 | J247: -0.0709 | K247: 1 | L247: 5 | M247: Win | N247: =IF(M247="Win",IF(F247="Bet",(I247-1)*K247,K247),IF(M247="Loss",IF(F247="Bet",-K247,-(I247-1)*K247),IF(M247="Void",0,""))) | O247: =IF(OR(M247="Win",M247="Loss"),IF(F247="Bet",K247,(I247-1)*K247),"")
A248: 46284 | B248: Wagga | C248: 2 | D248: 9 | E248: El Cool Gee | F248: Lay | G248: Lay | H248: 3.3 | I248: 2.65 | J248: -0.0634 | K248: 1 | L248: 2 | M248: Win | N248: =IF(M248="Win",IF(F248="Bet",(I248-1)*K248,K248),IF(M248="Loss",IF(F248="Bet",-K248,-(I248-1)*K248),IF(M248="Void",0,""))) | O248: =IF(OR(M248="Win",M248="Loss"),IF(F248="Bet",K248,(I248-1)*K248),"")
A249: 46284 | B249: Morphettville Parks | C249: 4 | D249: 6 | E249: Flirt | F249: Bet | G249: Bet | H249: 10.4 | I249: 21.26 | J249: 0.0297 | K249: 1 | L249: 3 | M249: Loss | N249: =IF(M249="Win",IF(F249="Bet",(I249-1)*K249,K249),IF(M249="Loss",IF(F249="Bet",-K249,-(I249-1)*K249),IF(M249="Void",0,""))) | O249: =IF(OR(M249="Win",M249="Loss"),IF(F249="Bet",K249,(I249-1)*K249),"")
A250: 46284 | B250: Morphettville Parks | C250: 9 | D250: 2 | E250: Nicish | F250: Lay | G250: Lay | H250: 4 | I250: 2.96 | J250: -0.0687 | K250: 1 | L250: 9 | M250: Win | N250: =IF(M250="Win",IF(F250="Bet",(I250-1)*K250,K250),IF(M250="Loss",IF(F250="Bet",-K250,-(I250-1)*K250),IF(M250="Void",0,""))) | O250: =IF(OR(M250="Win",M250="Loss"),IF(F250="Bet",K250,(I250-1)*K250),"")
A251: 46284 | B251: Caulfield | C251: 7 | D251: 1 | E251: Lindermann | F251: Lay | G251: Lay | H251: 3.7 | I251: 2.72 | J251: -0.0621 | K251: 1 | L251: 8 | M251: Win | N251: =IF(M251="Win",IF(F251="Bet",(I251-1)*K251,K251),IF(M251="Loss",IF(F251="Bet",-K251,-(I251-1)*K251),IF(M251="Void",0,""))) | O251: =IF(OR(M251="Win",M251="Loss"),IF(F251="Bet",K251,(I251-1)*K251),"")
A252: 46284 | B252: Morphettville Parks | C252: 4 | D252: 2 | E252: Codename | F252: Bet | G252: Bet | H252: 4.3 | I252: 7.5 | J252: 0.0233 | K252: 1 | L252: 5 | M252: Loss | N252: =IF(M252="Win",IF(F252="Bet",(I252-1)*K252,K252),IF(M252="Loss",IF(F252="Bet",-K252,-(I252-1)*K252),IF(M252="Void",0,""))) | O252: =IF(OR(M252="Win",M252="Loss"),IF(F252="Bet",K252,(I252-1)*K252),"")
A253: 46284 | B253: Randwick | C253: 7 | D253: 3 | E253: Striking Alibi | F253: Lay | G253: Lay | H253: 5.5 | I253: 3.1 | J253: -0.0807 | K253: 1 | L253: 2 | M253: Win | N253: =IF(M253="Win",IF(F253="Bet",(I253-1)*K253,K253),IF(M253="Loss",IF(F253="Bet",-K253,-(I253-1)*K253),IF(M253="Void",0,""))) | O253: =IF(OR(M253="Win",M253="Loss"),IF(F253="Bet",K253,(I253-1)*K253),"")
A254: 46284 | B254: Morphettville Parks | C254: 4 | D254: 9 | E254: Zoutrail | F254: Bet | G254: Bet | H254: 6.3 | I254: 9 | J254: 0.0468 | K254: 1 | L254: 6 | M254: Loss | N254: =IF(M254="Win",IF(F254="Bet",(I254-1)*K254,K254),IF(M254="Loss",IF(F254="Bet",-K254,-(I254-1)*K254),IF(M254="Void",0,""))) | O254: =IF(OR(M254="Win",M254="Loss"),IF(F254="Bet",K254,(I254-1)*K254),"")
A255: 46284 | B255: Gold Coast | C255: 2 | D255: 4 | E255: Weownachevy | F255: Lay | G255: Lay | H255: 4.3 | I255: 2.98 | J255: -0.0983 | K255: 1 | L255: 1 | M255: Loss | N255: =IF(M255="Win",IF(F255="Bet",(I255-1)*K255,K255),IF(M255="Loss",IF(F255="Bet",-K255,-(I255-1)*K255),IF(M255="Void",0,""))) | O255: =IF(OR(M255="Win",M255="Loss"),IF(F255="Bet",K255,(I255-1)*K255),"")
A256: 46284 | B256: Bowraville | C256: 7 | D256: 7 | E256: Enzoni | F256: Lay | G256: Lay | H256: 5.4 | I256: 3.35 | J256: -0.0759 | K256: 1 | L256: 5 | M256: Win | N256: =IF(M256="Win",IF(F256="Bet",(I256-1)*K256,K256),IF(M256="Loss",IF(F256="Bet",-K256,-(I256-1)*K256),IF(M256="Void",0,""))) | O256: =IF(OR(M256="Win",M256="Loss"),IF(F256="Bet",K256,(I256-1)*K256),"")
A257: 46284 | B257: Belmont | C257: 3 | D257: 1 | E257: Ginnivan | F257: Lay | G257: Lay | H257: 6 | I257: 3.2 | J257: -0.0601 | K257: 1 | L257: 7 | M257: Win | N257: =IF(M257="Win",IF(F257="Bet",(I257-1)*K257,K257),IF(M257="Loss",IF(F257="Bet",-K257,-(I257-1)*K257),IF(M257="Void",0,""))) | O257: =IF(OR(M257="Win",M257="Loss"),IF(F257="Bet",K257,(I257-1)*K257),"")
A258: 46284 | B258: Mt Magnet | C258: 6 | D258: 1 | E258: Another Nephew | F258: Lay | G258: Lay | H258: 2.9 | I258: 2.15 | J258: -0.0859 | K258: 1 | M258: Void | N258: =IF(M258="Win",IF(F258="Bet",(I258-1)*K258,K258),IF(M258="Loss",IF(F258="Bet",-K258,-(I258-1)*K258),IF(M258="Void",0,""))) | O258: =IF(OR(M258="Win",M258="Loss"),IF(F258="Bet",K258,(I258-1)*K258),"")
A259: 46284 | B259: Bowraville | C259: 5 | D259: 3 | E259: Checks'n'balances | F259: Bet | G259: Bet | H259: 4 | I259: 4.6 | J259: 0.034 | K259: 1 | L259: 7 | M259: Loss | N259: =IF(M259="Win",IF(F259="Bet",(I259-1)*K259,K259),IF(M259="Loss",IF(F259="Bet",-K259,-(I259-1)*K259),IF(M259="Void",0,""))) | O259: =IF(OR(M259="Win",M259="Loss"),IF(F259="Bet",K259,(I259-1)*K259),"")
...

Sheet Bets
O2: Bets
O3: Every bet, 11 Sep to 2 Oct 2026
A5: Date | B5: Track | C5: Race | D5: No. | E5: Horse | F5: Call | G5: Tag | H5: Rated $ | I5: Price $ | J5: Edge | K5: Stake (u) | L5: Finish | M5: Result | N5: Profit (u) | O5: At risk (u)
A6: 46276 | B6: Geelong | C6: 2 | D6: 5 | E6: Vespasian | F6: Bet | G6: Bet | H6: 6.3 | I6: 9.8 | J6: 0.0253 | K6: 1 | L6: 2 | M6: Loss | N6: =IF(M6="Win",IF(F6="Bet",(I6-1)*K6,K6),IF(M6="Loss",IF(F6="Bet",-K6,-(I6-1)*K6),IF(M6="Void",0,""))) | O6: =IF(OR(M6="Win",M6="Loss"),IF(F6="Bet",K6,(I6-1)*K6),"")
A7: 46276 | B7: Bordertown | C7: 3 | D7: 6 | E7: Splash Of White | F7: Bet | G7: Bet | H7: 7.6 | I7: 9.5 | J7: 0.0258 | K7: 1 | L7: 6 | M7: Loss | N7: =IF(M7="Win",IF(F7="Bet",(I7-1)*K7,K7),IF(M7="Loss",IF(F7="Bet",-K7,-(I7-1)*K7),IF(M7="Void",0,""))) | O7: =IF(OR(M7="Win",M7="Loss"),IF(F7="Bet",K7,(I7-1)*K7),"")
A8: 46276 | B8: Tuncurry | C8: 7 | D8: 1 | E8: It's A Knockout | F8: Bet | G8: Bet | H8: 6.5 | I8: 8.5 | J8: 0.0354 | K8: 1 | L8: 5 | M8: Loss | N8: =IF(M8="Win",IF(F8="Bet",(I8-1)*K8,K8),IF(M8="Loss",IF(F8="Bet",-K8,-(I8-1)*K8),IF(M8="Void",0,""))) | O8: =IF(OR(M8="Win",M8="Loss"),IF(F8="Bet",K8,(I8-1)*K8),"")
A9: 46276 | B9: Sunshine Coast | C9: 1 | D9: 1 | E9: Sealord | F9: Bet | G9: Prime | H9: 3.3 | I9: 4.2 | J9: 0.0617 | K9: 1 | L9: 4 | M9: Loss | N9: =IF(M9="Win",IF(F9="Bet",(I9-1)*K9,K9),IF(M9="Loss",IF(F9="Bet",-K9,-(I9-1)*K9),IF(M9="Void",0,""))) | O9: =IF(OR(M9="Win",M9="Loss"),IF(F9="Bet",K9,(I9-1)*K9),"")
A10: 46276 | B10: Sunshine Coast | C10: 8 | D10: 5 | E10: Brass Band | F10: Bet | G10: Bet | H10: 4.8 | I10: 6 | J10: 0.0432 | K10: 1 | L10: 3 | M10: Loss | N10: =IF(M10="Win",IF(F10="Bet",(I10-1)*K10,K10),IF(M10="Loss",IF(F10="Bet",-K10,-(I10-1)*K10),IF(M10="Void",0,""))) | O10: =IF(OR(M10="Win",M10="Loss"),IF(F10="Bet",K10,(I10-1)*K10),"")
A11: 46277 | B11: Gold Coast | C11: 8 | D11: 5 | E11: Lumens Lenny | F11: Bet | G11: Bet | H11: 5 | I11: 6.2 | J11: 0.0338 | K11: 1 | L11: 1 | M11: Win | N11: =IF(M11="Win",IF(F11="Bet",(I11-1)*K11,K11),IF(M11="Loss",IF(F11="Bet",-K11,-(I11-1)*K11),IF(M11="Void",0,""))) | O11: =IF(OR(M11="Win",M11="Loss"),IF(F11="Bet",K11,(I11-1)*K11),"")
A12: 46277 | B12: Flemington | C12: 3 | D12: 9 | E12: Lucky Brook | F12: Bet | G12: Bet | H12: 5.8 | I12: 7.5 | J12: 0.0382 | K12: 1 | L12: 8 | M12: Loss | N12: =IF(M12="Win",IF(F12="Bet",(I12-1)*K12,K12),IF(M12="Loss",IF(F12="Bet",-K12,-(I12-1)*K12),IF(M12="Void",0,""))) | O12: =IF(OR(M12="Win",M12="Loss"),IF(F12="Bet",K12,(I12-1)*K12),"")
A13: 46277 | B13: Flemington | C13: 6 | D13: 1 | E13: Cafe Millenium | F13: Bet | G13: Bet | H13: 5.5 | I13: 8.2 | J13: 0.0489 | K13: 1 | L13: 3 | M13: Loss | N13: =IF(M13="Win",IF(F13="Bet",(I13-1)*K13,K13),IF(M13="Loss",IF(F13="Bet",-K13,-(I13-1)*K13),IF(M13="Void",0,""))) | O13: =IF(OR(M13="Win",M13="Loss"),IF(F13="Bet",K13,(I13-1)*K13),"")
A14: 46277 | B14: Rosehill | C14: 2 | D14: 7 | E14: Formal | F14: Bet | G14: Bet | H14: 6.3 | I14: 9.68 | J14: 0.0348 | K14: 1 | L14: 1 | M14: Win | N14: =IF(M14="Win",IF(F14="Bet",(I14-1)*K14,K14),IF(M14="Loss",IF(F14="Bet",-K14,-(I14-1)*K14),IF(M14="Void",0,""))) | O14: =IF(OR(M14="Win",M14="Loss"),IF(F14="Bet",K14,(I14-1)*K14),"")
A15: 46277 | B15: Rosehill | C15: 3 | D15: 4 | E15: Golden Century | F15: Bet | G15: Prime | H15: 3.3 | I15: 5.13 | J15: 0.0958 | K15: 1 | L15: 4 | M15: Loss | N15: =IF(M15="Win",IF(F15="Bet",(I15-1)*K15,K15),IF(M15="Loss",IF(F15="Bet",-K15,-(I15-1)*K15),IF(M15="Void",0,""))) | O15: =IF(OR(M15="Win",M15="Loss"),IF(F15="Bet",K15,(I15-1)*K15),"")
A16: 46277 | B16: Rosehill | C16: 7 | D16: 2 | E16: Lazzura | F16: Bet | G16: Prime | H16: 2.55 | I16: 3.25 | J16: 0.0597 | K16: 1 | L16: 3 | M16: Loss | N16: =IF(M16="Win",IF(F16="Bet",(I16-1)*K16,K16),IF(M16="Loss",IF(F16="Bet",-K16,-(I16-1)*K16),IF(M16="Void",0,""))) | O16: =IF(OR(M16="Win",M16="Loss"),IF(F16="Bet",K16,(I16-1)*K16),"")
A17: 46277 | B17: Doomben | C17: 3 | D17: 4 | E17: Perfect Play | F17: Bet | G17: Bet | H17: 4.7 | I17: 5.72 | J17: 0.0319 | K17: 1 | L17: 4 | M17: Loss | N17: =IF(M17="Win",IF(F17="Bet",(I17-1)*K17,K17),IF(M17="Loss",IF(F17="Bet",-K17,-(I17-1)*K17),IF(M17="Void",0,""))) | O17: =IF(OR(M17="Win",M17="Loss"),IF(F17="Bet",K17,(I17-1)*K17),"")
... A40: 46278 | B40: Northam | C40: 1 | D40: 1 | E40: Who's Bent | F40: Bet | G40: Bet | H40: 3.5 | I40: 4.2 | J40: 0.0477 | K40: 1 | L40: 1 | M40: Win | N40: =IF(M40="Win",IF(F40="Bet",(I40-1)*K40,K40),IF(M40="Loss",IF(F40="Bet",-K40,-(I40-1)*K40),IF(M40="Void",0,""))) | O40: =IF(OR(M40="Win",M40="Loss"),IF(F40="Bet",K40,(I40-1)*K40),"")
A41: 46278 | B41: Bathurst | C41: 7 | D41: 2 | E41: Fearn Trick | F41: Bet | G41: Bet | H41: 7.5 | I41: 9.5 | J41: 0.0279 | K41: 1 | M41: Void | N41: =IF(M41="Win",IF(F41="Bet",(I41-1)*K41,K41),IF(M41="Loss",IF(F41="Bet",-K41,-(I41-1)*K41),IF(M41="Void",0,""))) | O41: =IF(OR(M41="Win",M41="Loss"),IF(F41="Bet",K41,(I41-1)*K41),"")
A42: 46279 | B42: Tamworth | C42: 4 | D42: 2 | E42: Mongolian Master | F42: Bet | G42: Bet | H42: 6.9 | I42: 9.6 | J42: 0.0335 | K42: 1 | L42: 3 | M42: Loss | N42: =IF(M42="Win",IF(F42="Bet",(I42-1)*K42,K42),IF(M42="Loss",IF(F42="Bet",-K42,-(I42-1)*K42),IF(M42="Void",0,""))) | O42: =IF(OR(M42="Win",M42="Loss"),IF(F42="Bet",K42,(I42-1)*K42),"")
A43: 46279 | B43: Tamworth | C43: 6 | D43: 2 | E43: He's My Warrior | F43: Bet | G43: Bet | H43: 6.5 | I43: 8 | J43: 0.0286 | K43: 1 | L43: 6 | M43: Loss | N43: =IF(M43="Win",IF(F43="Bet",(I43-1)*K43,K43),IF(M43="Loss",IF(F43="Bet",-K43,-(I43-1)*K43),IF(M43="Void",0,""))) | O43: =IF(OR(M43="Win",M43="Loss"),IF(F43="Bet",K43,(I43-1)*K43),"")
A44: 46279 | B44: Corowa | C44: 3 | D44: 2 | E44: Canny Hell | F44: Bet | G44: Prime | H44: 2.55 | I44: 3.95 | J44: 0.0792 | K44: 1 | L44: 2 | M44: Loss | N44: =IF(M44="Win",IF(F44="Bet",(I44-1)*K44,K44),IF(M44="Loss",IF(F44="Bet",-K44,-(I44-1)*K44),IF(M44="Void",0,""))) | O44: =IF(OR(M44="Win",M44="Loss"),IF(F44="Bet",K44,(I44-1)*K44),"")
A45: 46280 | B45: Moruya | C45: 5 | D45: 2 | E45: Nights Inferno | F45: Bet | G45: Bet | H45: 5.5 | I45: 6.8 | J45: 0.0271 | K45: 1 | L45: 4 | M45: Loss | N45: =IF(M45="Win",IF(F45="Bet",(I45-1)*K45,K45),IF(M45="Loss",IF(F45="Bet",-K45,-(I45-1)*K45),IF(M45="Void",0,""))) | O45: =IF(OR(M45="Win",M45="Loss"),IF(F45="Bet",K45,(I45-1)*K45),"")
A46: 46280 | B46: Bowen | C46: 1 | D46: 4 | E46: Missile Baby | F46: Bet | G46: Prime | H46: 4.1 | I46: 6.22 | J46: 0.0647 | K46: 1 | L46: 3 | M46: Loss | N46: =IF(M46="Win",IF(F46="Bet",(I46-1)*K46,K46),IF(M46="Loss",IF(F46="Bet",-K46,-(I46-1)*K46),IF(M46="Void",0,""))) | O46: =IF(OR(M46="Win",M46="Loss"),IF(F46="Bet",K46,(I46-1)*K46),"")
A47: 46281 | B47: Doomben | C47: 1 | D47: 1 | E47: Bacetti | F47: Bet | G47: Bet | H47: 6.1 | I47: 9.54 | J47: 0.0296 | K47: 1 | L47: 3 | M47: Loss | N47: =IF(M47="Win",IF(F47="Bet",(I47-1)*K47,K47),IF(M47="Loss",IF(F47="Bet",-K47,-(I47-1)*K47),IF(M47="Void",0,""))) | O47: =IF(OR(M47="Win",M47="Loss"),IF(F47="Bet",K47,(I47-1)*K47),"")
A48: 46281 | B48: Caulfield Heath | C48: 4 | D48: 13 | E48: Tuzemak | F48: Bet | G48: Bet | H48: 9.7 | I48: 17 | J48: 0.026 | K48: 1 | L48: 6 | M48: Loss | N48: =IF(M48="Win",IF(F48="Bet",(I48-1)*K48,K48),IF(M48="Loss",IF(F48="Bet",-K48,-(I48-1)*K48),IF(M48="Void",0,""))) | O48: =IF(OR(M48="Win",M48="Loss"),IF(F48="Bet",K48,(I48-1)*K48),"")
A49: 46281 | B49: Caulfield Heath | C49: 2 | D49: 4 | E49: All Business | F49: Bet | G49: Bet | H49: 6 | I49: 7.5 | J49: 0.0335 | K49: 1 | L49: 1 | M49: Win | N49: =IF(M49="Win",IF(F49="Bet",(I49-1)*K49,K49),IF(M49="Loss",IF(F49="Bet",-K49,-(I49-1)*K49),IF(M49="Void",0,""))) | O49: =IF(OR(M49="Win",M49="Loss"),IF(F49="Bet",K49,(I49-1)*K49),"")
A50: 46281 | B50: Belmont | C50: 2 | D50: 1 | E50: Rocking In Vegas | F50: Bet | G50: Prime | H50: 4.6 | I50: 14.5 | J50: 0.1018 | K50: 1 | L50: 3 | M50: Loss | N50: =IF(M50="Win",IF(F50="Bet",(I50-1)*K50,K50),IF(M50="Loss",IF(F50="Bet",-K50,-(I50-1)*K50),IF(M50="Void",0,""))) | O50: =IF(OR(M50="Win",M50="Loss"),IF(F50="Bet",K50,(I50-1)*K50),"")
A51: 46281 | B51: Belmont | C51: 3 | D51: 4 | E51: Wiluna Lass | F51: Bet | G51: Bet | H51: 4.3 | I51: 5.5 | J51: 0.0264 | K51: 1 | L51: 1 | M51: Win | N51: =IF(M51="Win",IF(F51="Bet",(I51-1)*K51,K51),IF(M51="Loss",IF(F51="Bet",-K51,-(I51-1)*K51),IF(M51="Void",0,""))) | O51: =IF(OR(M51="Win",M51="Loss"),IF(F51="Bet",K51,(I51-1)*K51),"")
A52: 46281 | B52: Launceston | C52: 2 | D52: 3 | E52: Lin Thizzy | F52: Bet | G52: Bet | H52: 3.4 | I52: 8.6 | J52: 0.0414 | K52: 1 | L52: 1 | M52: Win | N52: =IF(M52="Win",IF(F52="Bet",(I52-1)*K52,K52),IF(M52="Loss",IF(F52="Bet",-K52,-(I52-1)*K52),IF(M52="Void",0,""))) | O52: =IF(OR(M52="Win",M52="Loss"),IF(F52="Bet",K52,(I52-1)*K52),"")
A53: 46281 | B53: Canterbury | C53: 2 | D53: 6 | E53: Saffron Veil | F53: Bet | G53: Bet | H53: 1.8 | I53: 2.1 | J53: 0.0407 | K53: 1 | L53: 1 | M53: Win | N53: =IF(M53="Win",IF(F53="Bet",(I53-1)*K53,K53),IF(M53="Loss",IF(F53="Bet",-K53,-(I53-1)*K53),IF(M53="Void",0,""))) | O53: =IF(OR(M53="Win",M53="Loss"),IF(F53="Bet",K53,(I53-1)*K53),"")
... A55: 46281 | B55: Balaklava | C55: 1 | D55: 5 | E55: Leading Ride | F55: Bet | G55: Bet | H55: 4.6 | I55: 10.98 | J55: 0.037 | K55: 1 | L55: 3 | M55: Loss | N55: =IF(M55="Win",IF(F55="Bet",(I55-1)*K55,K55),IF(M55="Loss",IF(F55="Bet",-K55,-(I55-1)*K55),IF(M55="Void",0,""))) | O55: =IF(OR(M55="Win",M55="Loss"),IF(F55="Bet",K55,(I55-1)*K55),"")
A56: 46281 | B56: Caulfield Heath | C56: 2 | D56: 2 | E56: Lake Vostok | F56: Bet | G56: Bet | H56: 5.6 | I56: 7 | J56: 0.0355 | K56: 1 | M56: Void | N56: =IF(M56="Win",IF(F56="Bet",(I56-1)*K56,K56),IF(M56="Loss",IF(F56="Bet",-K56,-(I56-1)*K56),IF(M56="Void",0,""))) | O56: =IF(OR(M56="Win",M56="Loss"),IF(F56="Bet",K56,(I56-1)*K56),"")
A57: 46281 | B57: Caulfield Heath | C57: 1 | D57: 1 | E57: Corviglia | F57: Bet | G57: Prime | H57: 5.3 | I57: 9.36 | J57: 0.065 | K57: 1 | L57: 2 | M57: Loss | N57: =IF(M57="Win",IF(F57="Bet",(I57-1)*K57,K57),IF(M57="Loss",IF(F57="Bet",-K57,-(I57-1)*K57),IF(M57="Void",0,""))) | O57: =IF(OR(M57="Win",M57="Loss"),IF(F57="Bet",K57,(I57-1)*K57),"")
A58: 46281 | B58: Balaklava | C58: 1 | D58: 1 | E58: Sidebar | F58: Bet | G58: Bet | H58: 5.9 | I58: 10.5 | J58: 0.0262 | K58: 1 | L58: 4 | M58: Loss | N58: =IF(M58="Win",IF(F58="Bet",(I58-1)*K58,K58),IF(M58="Loss",IF(F58="Bet",-K58,-(I58-1)*K58),IF(M58="Void",0,""))) | O58: =IF(OR(M58="Win",M58="Loss"),IF(F58="Bet",K58,(I58-1)*K58),"")
A59: 46281 | B59: Doomben | C59: 3 | D59: 9 | E59: Flaressence | F59: Bet | G59: Bet | H59: 3.9 | I59: 6 | J59: 0.0388 | K59: 1 | L59: 2 | M59: Loss | N59: =IF(M59="Win",IF(F59="Bet",(I59-1)*K59,K59),IF(M59="Loss",IF(F59="Bet",-K59,-(I59-1)*K59),IF(M59="Void",0,""))) | O59: =IF(OR(M59="Win",M59="Loss"),IF(F59="Bet",K59,(I59-1)*K59),"")
A60: 46281 | B60: Caulfield Heath | C60: 7 | D60: 4 | E60: Rhapsody Chic | F60: Bet | G60: Bet | H60: 11.7 | I60: 31 | J60: 0.0264 | K60: 1 | L60: 8 | M60: Loss | N60: =IF(M60="Win",IF(F60="Bet",(I60-1)*K60,K60),IF(M60="Loss",IF(F60="Bet",-K60,-(I60-1)*K60),IF(M60="Void",0,""))) | O60: =IF(OR(M60="Win",M60="Loss"),IF(F60="Bet",K60,(I60-1)*K60),"")
A61: 46281 | B61: Canterbury | C61: 5 | D61: 1 | E61: Tremonti | F61: Bet | G61: Bet | H61: 9.1 | I61: 21 | J61: 0.0426 | K61: 1 | L61: 10 | M61: Loss | N61: =IF(M61="Win",IF(F61="Bet",(I61-1)*K61,K61),IF(M61="Loss",IF(F61="Bet",-K61,-(I61-1)*K61),IF(M61="Void",0,""))) | O61: =IF(OR(M61="Win",M61="Loss"),IF(F61="Bet",K61,(I61-1)*K61),"")
A62: 46281 | B62: Balaklava | C62: 8 | D62: 1 | E62: Super Lad | F62: Bet | G62: Bet | H62: 5.2 | I62: 6 | J62: 0.0257 | K62: 1 | L62: 5 | M62: Loss | N62: =IF(M62="Win",IF(F62="Bet",(I62-1)*K62,K62),IF(M62="Loss",IF(F62="Bet",-K62,-(I62-1)*K62),IF(M62="Void",0,""))) | O62: =IF(OR(M62="Win",M62="Loss"),IF(F62="Bet",K62,(I62-1)*K62),"")
A63: 46281 | B63: Doomben | C63: 5 | D63: 3 | E63: Captain Eagle | F63: Bet | G63: Bet | H63: 8.6 | I63: 11 | J63: 0.0252 | K63: 1 | L63: 8 | M63: Loss | N63: =IF(M63="Win",IF(F63="Bet",(I63-1)*K63,K63),IF(M63="Loss",IF(F63="Bet",-K63,-(I63-1)*K63),IF(M63="Void",0,""))) | O63: =IF(OR(M63="Win",M63="Loss"),IF(F63="Bet",K63,(I63-1)*K63),"")
A64: 46281 | B64: Canterbury | C64: 7 | D64: 9 | E64: Rileycat | F64: Bet | G64: Bet | H64: 11.7 | I64: 17 | J64: 0.027 | K64: 1 | L64: 10 | M64: Loss | N64: =IF(M64="Win",IF(F64="Bet",(I64-1)*K64,K64),IF(M64="Loss",IF(F64="Bet",-K64,-(I64-1)*K64),IF(M64="Void",0,""))) | O64: =IF(OR(M64="Win",M64="Loss"),IF(F64="Bet",K64,(I64-1)*K64),"")
A65: 46281 | B65: Caulfield Heath | C65: 7 | D65: 3 | E65: Angland | F65: Bet | G65: Bet | H65: 10.3 | I65: 14 | J65: 0.0255 | K65: 1 | L65: 3 | M65: Loss | N65: =IF(M65="Win",IF(F65="Bet",(I65-1)*K65,K65),IF(M65="Loss",IF(F65="Bet",-K65,-(I65-1)*K65),IF(M65="Void",0,""))) | O65: =IF(OR(M65="Win",M65="Loss"),IF(F65="Bet",K65,(I65-1)*K65),"")
A66: 46283 | B66: Canberra | C66: 1 | D66: 2 | E66: Unmatched | F66: Bet | G66: Prime | H66: 5.2 | I66: 9.64 | J66: 0.027 | K66: 1 | L66: 3 | M66: Loss | N66: =IF(M66="Win",IF(F66="Bet",(I66-1)*K66,K66),IF(M66="Loss",IF(F66="Bet",-K66,-(I66-1)*K66),IF(M66="Void",0,""))) | O66: =IF(OR(M66="Win",M66="Loss"),IF(F66="Bet",K66,(I66-1)*K66),"")
A67: 46283 | B67: Canberra | C67: 5 | D67: 3 | E67: Shaft Attack | F67: Bet | G67: Bet | H67: 6.3 | I67: 7.5 | J67: 0.0255 | K67: 1 | L67: 2 | M67: Loss | N67: =IF(M67="Win",IF(F67="Bet",(I67-1)*K67,K67),IF(M67="Loss",IF(F67="Bet",-K67,-(I67-1)*K67),IF(M67="Void",0,""))) | O67: =IF(OR(M67="Win",M67="Loss"),IF(F67="Bet",K67,(I67-1)*K67),"")
A68: 46283 | B68: Townsville | C68: 8 | D68: 2 | E68: New Hampshire | F68: Bet | G68: Bet | H68: 11.3 | I68: 81 | J68: 0.0499 | K68: 1 | L68: 8 | M68: Loss | N68: =IF(M68="Win",IF(F68="Bet",(I68-1)*K68,K68),IF(M68="Loss",IF(F68="Bet",-K68,-(I68-1)*K68),IF(M68="Void",0,""))) | O68: =IF(OR(M68="Win",M68="Loss"),IF(F68="Bet",K68,(I68-1)*K68),"")
... A90: 46284 | B90: Belmont | C90: 4 | D90: 1 | E90: Too Dardy | F90: Bet | G90: Bet | H90: 4.7 | I90: 5.5 | J90: 0.0317 | K90: 1 | L90: 2 | M90: Loss | N90: =IF(M90="Win",IF(F90="Bet",(I90-1)*K90,K90),IF(M90="Loss",IF(F90="Bet",-K90,-(I90-1)*K90),IF(M90="Void",0,""))) | O90: =IF(OR(M90="Win",M90="Loss"),IF(F90="Bet",K90,(I90-1)*K90),"")
A91: 46284 | B91: Gold Coast | C91: 3 | D91: 11 | E91: Brain Wave | F91: Bet | G91: Bet | H91: 8.7 | I91: 12 | J91: 0.0318 | K91: 1 | M91: Void | N91: =IF(M91="Win",IF(F91="Bet",(I91-1)*K91,K91),IF(M91="Loss",IF(F91="Bet",-K91,-(I91-1)*K91),IF(M91="Void",0,""))) | O91: =IF(OR(M91="Win",M91="Loss"),IF(F91="Bet",K91,(I91-1)*K91),"")
A92: 46284 | B92: Eagle Farm | C92: 6 | D92: 1 | E92: Midnight Spirit | F92: Bet | G92: Bet | H92: 8.1 | I92: 11 | J92: 0.0325 | K92: 1 | L92: 3 | M92: Loss | N92: =IF(M92="Win",IF(F92="Bet",(I92-1)*K92,K92),IF(M92="Loss",IF(F92="Bet",-K92,-(I92-1)*K92),IF(M92="Void",0,""))) | O92: =IF(OR(M92="Win",M92="Loss"),IF(F92="Bet",K92,(I92-1)*K92),"")
A93: 46284 | B93: Eagle Farm | C93: 6 | D93: 11 | E93: Miss Funny Honey | F93: Bet | G93: Bet | H93: 11.7 | I93: 16 | J93: 0.0231 | K93: 1 | M93: Void | N93: =IF(M93="Win",IF(F93="Bet",(I93-1)*K93,K93),IF(M93="Loss",IF(F93="Bet",-K93,-(I93-1)*K93),IF(M93="Void",0,""))) | O93: =IF(OR(M93="Win",M93="Loss"),IF(F93="Bet",K93,(I93-1)*K93),"")
A94: 46284 | B94: Morphettville Parks | C94: 4 | D94: 6 | E94: Flirt | F94: Bet | G94: Bet | H94: 10.4 | I94: 21.26 | J94: 0.0297 | K94: 1 | L94: 3 | M94: Loss | N94: =IF(M94="Win",IF(F94="Bet",(I94-1)*K94,K94),IF(M94="Loss",IF(F94="Bet",-K94,-(I94-1)*K94),IF(M94="Void",0,""))) | O94: =IF(OR(M94="Win",M94="Loss"),IF(F94="Bet",K94,(I94-1)*K94),"")
A95: 46284 | B95: Morphettville Parks | C95: 4 | D95: 2 | E95: Codename | F95: Bet | G95: Bet | H95: 4.3 | I95: 7.5 | J95: 0.0233 | K95: 1 | L95: 5 | M95: Loss | N95: =IF(M95="Win",IF(F95="Bet",(I95-1)*K95,K95),IF(M95="Loss",IF(F95="Bet",-K95,-(I95-1)*K95),IF(M95="Void",0,""))) | O95: =IF(OR(M95="Win",M95="Loss"),IF(F95="Bet",K95,(I95-1)*K95),"")
A96: 46284 | B96: Morphettville Parks | C96: 4 | D96: 9 | E96: Zoutrail | F96: Bet | G96: Bet | H96: 6.3 | I96: 9 | J96: 0.0468 | K96: 1 | L96: 6 | M96: Loss | N96: =IF(M96="Win",IF(F96="Bet",(I96-1)*K96,K96),IF(M96="Loss",IF(F96="Bet",-K96,-(I96-1)*K96),IF(M96="Void",0,""))) | O96: =IF(OR(M96="Win",M96="Loss"),IF(F96="Bet",K96,(I96-1)*K96),"")
A97: 46284 | B97: Bowraville | C97: 5 | D97: 3 | E97: Checks'n'balances | F97: Bet | G97: Bet | H97: 4 | I97: 4.6 | J97: 0.034 | K97: 1 | L97: 7 | M97: Loss | N97: =IF(M97="Win",IF(F97="Bet",(I97-1)*K97,K97),IF(M97="Loss",IF(F97="Bet",-K97,-(I97-1)*K97),IF(M97="Void",0,""))) | O97: =IF(OR(M97="Win",M97="Loss"),IF(F97="Bet",K97,(I97-1)*K97),"")
A98: 46284 | B98: Bowraville | C98: 5 | D98: 4 | E98: Raining Luck | F98: Bet | G98: Way | H98: 15.9 | I98: 51 | J98: 0.0433 | K98: 0.1 | L98: 3 | M98: Loss | N98: =IF(M98="Win",IF(F98="Bet",(I98-1)*K98,K98),IF(M98="Loss",IF(F98="Bet",-K98,-(I98-1)*K98),IF(M98="Void",0,""))) | O98: =IF(OR(M98="Win",M98="Loss"),IF(F98="Bet",K98,(I98-1)*K98),"")
A99: 46284 | B99: Bowraville | C99: 5 | D99: 8 | E99: Sizzling Suzie | F99: Bet | G99: Bet | H99: 8.9 | I99: 19 | J99: 0.0593 | K99: 1 | L99: 4 | M99: Loss | N99: =IF(M99="Win",IF(F99="Bet",(I99-1)*K99,K99),IF(M99="Loss",IF(F99="Bet",-K99,-(I99-1)*K99),IF(M99="Void",0,""))) | O99: =IF(OR(M99="Win",M99="Loss"),IF(F99="Bet",K99,(I99-1)*K99),"")
A100: 46284 | B100: Bowraville | C100: 5 | D100: 9 | E100: Ronardo | F100: Bet | G100: Bet | H100: 6.6 | I100: 15.5 | J100: 0.0261 | K100: 1 | L100: 2 | M100: Loss | N100: =IF(M100="Win",IF(F100="Bet",(I100-1)*K100,K100),IF(M100="Loss",IF(F100="Bet",-K100,-(I100-1)*K100),IF(M100="Void",0,""))) | O100: =IF(OR(M100="Win",M100="Loss"),IF(F100="Bet",K100,(I100-1)*K100),"")
A101: 46284 | B101: Bowraville | C101: 5 | D101: 6 | E101: The Michael | F101: Bet | G101: Way | H101: 25.3 | I101: 81 | J101: 0.0272 | K101: 0.1 | L101: 5 | M101: Loss | N101: =IF(M101="Win",IF(F101="Bet",(I101-1)*K101,K101),IF(M101="Loss",IF(F101="Bet",-K101,-(I101-1)*K101),IF(M101="Void",0,""))) | O101: =IF(OR(M101="Win",M101="Loss"),IF(F101="Bet",K101,(I101-1)*K101),"")
A102: 46284 | B102: Bowraville | C102: 5 | D102: 1 | E102: Bon Batan | F102: Bet | G102: Way | H102: 12.7 | I102: 29 | J102: 0.0444 | K102: 0.1 | L102: 6 | M102: Loss | N102: =IF(M102="Win",IF(F102="Bet",(I102-1)*K102,K102),IF(M102="Loss",IF(F102="Bet",-K102,-(I102-1)*K102),IF(M102="Void",0,""))) | O102: =IF(OR(M102="Win",M102="Loss"),IF(F102="Bet",K102,(I102-1)*K102),"")
A103: 46284 | B103: Bowraville | C103: 5 | D103: 5 | E103: Strenuous | F103: Bet | G103: Prime | H103: 3.6 | I103: 4.6 | J103: 0.0634 | K103: 1 | L103: 1 | M103: Win | N103: =IF(M103="Win",IF(F103="Bet",(I103-1)*K103,K103),IF(M103="Loss",IF(F103="Bet",-K103,-(I103-1)*K103),IF(M103="Void",0,""))) | O103: =IF(OR(M103="Win",M103="Loss"),IF(F103="Bet",K103,(I103-1)*K103),"")
A104: 46284 | B104: Eagle Farm | C104: 8 | D104: 6 | E104: Ciphertext | F104: Bet | G104: Bet | H104: 9.5 | I104: 13 | J104: 0.0282 | K104: 1 | L104: 5 | M104: Loss | N104: =IF(M104="Win",IF(F104="Bet",(I104-1)*K104,K104),IF(M104="Loss",IF(F104="Bet",-K104,-(I104-1)*K104),IF(M104="Void",0,""))) | O104: =IF(OR(M104="Win",M104="Loss"),IF(F104="Bet",K104,(I104-1)*K104),"")
A105: 46284 | B105: Eagle Farm | C105: 8 | D105: 8 | E105: Life After Love | F105: Bet | G105: Bet | H105: 7.9 | I105: 13 | J105: 0.0501 | K105: 1 | L105: 4 | M105: Loss | N105: =IF(M105="Win",IF(F105="Bet",(I105-1)*K105,K105),IF(M105="Loss",IF(F105="Bet",-K105,-(I105-1)*K105),IF(M105="Void",0,""))) | O105: =IF(OR(M105="Win",M105="Loss"),IF(F105="Bet",K105,(I105-1)*K105),"")
... A121: 46284 | B121: Bowraville | C121: 4 | D121: 1 | E121: Farraige | F121: Bet | G121: Bet | H121: 6.9 | I121: 11 | J121: 0.0203 | K121: 1 | L121: 2 | M121: Loss | N121: =IF(M121="Win",IF(F121="Bet",(I121-1)*K121,K121),IF(M121="Loss",IF(F121="Bet",-K121,-(I121-1)*K121),IF(M121="Void",0,""))) | O121: =IF(OR(M121="Win",M121="Loss"),IF(F121="Bet",K121,(I121-1)*K121),"")
A122: 46284 | B122: Mt Magnet | C122: 1 | D122: 2 | E122: Ginger Fizz | F122: Bet | G122: Bet | H122: 8.8 | I122: 12 | J122: 0.0232 | K122: 1 | M122: Void | N122: =IF(M122="Win",IF(F122="Bet",(I122-1)*K122,K122),IF(M122="Loss",IF(F122="Bet",-K122,-(I122-1)*K122),IF(M122="Void",0,""))) | O122: =IF(OR(M122="Win",M122="Loss"),IF(F122="Bet",K122,(I122-1)*K122),"")
A123: 46284 | B123: Randwick | C123: 8 | D123: 2 | E123: Gringotts | F123: Bet | G123: Bet | H123: 10.8 | I123: 14 | J123: 0.0212 | K123: 1 | L123: 5 | M123: Loss | N123: =IF(M123="Win",IF(F123="Bet",(I123-1)*K123,K123),IF(M123="Loss",IF(F123="Bet",-K123,-(I123-1)*K123),IF(M123="Void",0,""))) | O123: =IF(OR(M123="Win",M123="Loss"),IF(F123="Bet",K123,(I123-1)*K123),"")
A124: 46284 | B124: Belmont | C124: 3 | D124: 3 | E124: Platinum Shot | F124: Bet | G124: Bet | H124: 11.4 | I124: 30.46 | J124: 0.0211 | K124: 1 | L124: 4 | M124: Loss | N124: =IF(M124="Win",IF(F124="Bet",(I124-1)*K124,K124),IF(M124="Loss",IF(F124="Bet",-K124,-(I124-1)*K124),IF(M124="Void",0,""))) | O124: =IF(OR(M124="Win",M124="Loss"),IF(F124="Bet",K124,(I124-1)*K124),"")
A125: 46284 | B125: Belmont | C125: 3 | D125: 8 | E125: Country God | F125: Bet | G125: Bet | H125: 4.9 | I125: 6.53 | J125: 0.0212 | K125: 1 | L125: 2 | M125: Loss | N125: =IF(M125="Win",IF(F125="Bet",(I125-1)*K125,K125),IF(M125="Loss",IF(F125="Bet",-K125,-(I125-1)*K125),IF(M125="Void",0,""))) | O125: =IF(OR(M125="Win",M125="Loss"),IF(F125="Bet",K125,(I125-1)*K125),"")
A126: 46284 | B126: Gold Coast | C126: 9 | D126: 2 | E126: Pocketmoney | F126: Bet | G126: Bet | H126: 8.9 | I126: 11 | J126: 0.0215 | K126: 1 | L126: 5 | M126: Loss | N126: =IF(M126="Win",IF(F126="Bet",(I126-1)*K126,K126),IF(M126="Loss",IF(F126="Bet",-K126,-(I126-1)*K126),IF(M126="Void",0,""))) | O126: =IF(OR(M126="Win",M126="Loss"),IF(F126="Bet",K126,(I126-1)*K126),"")
A127: 46284 | B127: Morphettville Parks | C127: 9 | D127: 1 | E127: Scandalize | F127: Bet | G127: Bet | H127: 12.1 | I127: 21 | J127: 0.0201 | K127: 1 | L127: 8 | M127: Loss | N127: =IF(M127="Win",IF(F127="Bet",(I127-1)*K127,K127),IF(M127="Loss",IF(F127="Bet",-K127,-(I127-1)*K127),IF(M127="Void",0,""))) | O127: =IF(OR(M127="Win",M127="Loss"),IF(F127="Bet",K127,(I127-1)*K127),"")
A128: 46284 | B128: Belmont | C128: 7 | D128: 4 | E128: Diamond Dancer | F128: Bet | G128: Bet | H128: 11.5 | I128: 15 | J128: 0.0202 | K128: 1 | L128: 7 | M128: Loss | N128: =IF(M128="Win",IF(F128="Bet",(I128-1)*K128,K128),IF(M128="Loss",IF(F128="Bet",-K128,-(I128-1)*K128),IF(M128="Void",0,""))) | O128: =IF(OR(M128="Win",M128="Loss"),IF(F128="Bet",K128,(I128-1)*K128),"")
A129: 46285 | B129: Armidale | C129: 4 | D129: 9 | E129: Gyra | F129: Bet | G129: Bet | H129: 6.7 | I129: 26 | J129: 0.0967 | K129: 1 | L129: 7 | M129: Loss | N129: =IF(M129="Win",IF(F129="Bet",(I129-1)*K129,K129),IF(M129="Loss",IF(F129="Bet",-K129,-(I129-1)*K129),IF(M129="Void",0,""))) | O129: =IF(OR(M129="Win",M129="Loss"),IF(F129="Bet",K129,(I129-1)*K129),"")
A130: 46285 | B130: Armidale | C130: 3 | D130: 6 | E130: Slugworth | F130: Bet | G130: Prime | H130: 4.9 | I130: 11 | J130: 0.0503 | K130: 1 | L130: 10 | M130: Loss | N130: =IF(M130="Win",IF(F130="Bet",(I130-1)*K130,K130),IF(M130="Loss",IF(F130="Bet",-K130,-(I130-1)*K130),IF(M130="Void",0,""))) | O130: =IF(OR(M130="Win",M130="Loss"),IF(F130="Bet",K130,(I130-1)*K130),"")
A131: 46285 | B131: Bendigo | C131: 6 | D131: 9 | E131: Moral Turpitude | F131: Bet | G131: Way | H131: 19.9 | I131: 101 | J131: 0.0307 | K131: 0.1 | L131: 8 | M131: Loss | N131: =IF(M131="Win",IF(F131="Bet",(I131-1)*K131,K131),IF(M131="Loss",IF(F131="Bet",-K131,-(I131-1)*K131),IF(M131="Void",0,""))) | O131: =IF(OR(M131="Win",M131="Loss"),IF(F131="Bet",K131,(I131-1)*K131),"")
A132: 46285 | B132: Armidale | C132: 5 | D132: 7 | E132: Extreme Merger | F132: Bet | G132: Bet | H132: 11.5 | I132: 15 | J132: 0.02 | K132: 1 | L132: 8 | M132: Loss | N132: =IF(M132="Win",IF(F132="Bet",(I132-1)*K132,K132),IF(M132="Loss",IF(F132="Bet",-K132,-(I132-1)*K132),IF(M132="Void",0,""))) | O132: =IF(OR(M132="Win",M132="Loss"),IF(F132="Bet",K132,(I132-1)*K132),"")
A133: 46285 | B133: Nowra | C133: 4 | D133: 1 | E133: Winning Point | F133: Bet | G133: Bet | H133: 9 | I133: 15 | J133: 0.02 | K133: 1 | L133: 4 | M133: Loss | N133: =IF(M133="Win",IF(F133="Bet",(I133-1)*K133,K133),IF(M133="Loss",IF(F133="Bet",-K133,-(I133-1)*K133),IF(M133="Void",0,""))) | O133: =IF(OR(M133="Win",M133="Loss"),IF(F133="Bet",K133,(I133-1)*K133),"")
A134: 46285 | B134: Nowra | C134: 5 | D134: 1 | E134: Kiss Of Gold | F134: Bet | G134: Bet | H134: 8 | I134: 11.5 | J134: 0.0201 | K134: 1 | L134: 4 | M134: Loss | N134: =IF(M134="Win",IF(F134="Bet",(I134-1)*K134,K134),IF(M134="Loss",IF(F134="Bet",-K134,-(I134-1)*K134),IF(M134="Void",0,""))) | O134: =IF(OR(M134="Win",M134="Loss"),IF(F134="Bet",K134,(I134-1)*K134),"")
... A140: 46285 | B140: Sunshine Coast | C140: 4 | D140: 8 | E140: Makamae | F140: Bet | G140: Bet | H140: 4.3 | I140: 4.8 | J140: 0.0255 | K140: 1 | L140: 2 | M140: Loss | N140: =IF(M140="Win",IF(F140="Bet",(I140-1)*K140,K140),IF(M140="Loss",IF(F140="Bet",-K140,-(I140-1)*K140),IF(M140="Void",0,""))) | O140: =IF(OR(M140="Win",M140="Loss"),IF(F140="Bet",K140,(I140-1)*K140),"")
A141: 46285 | B141: Nowra | C141: 1 | D141: 8 | E141: Stormy Reign | F141: Bet | G141: Bet | H141: 6 | I141: 8.5 | J141: 0.0225 | K141: 1 | M141: Void | N141: =IF(M141="Win",IF(F141="Bet",(I141-1)*K141,K141),IF(M141="Loss",IF(F141="Bet",-K141,-(I141-1)*K141),IF(M141="Void",0,""))) | O141: =IF(OR(M141="Win",M141="Loss"),IF(F141="Bet",K141,(I141-1)*K141),"")
A142: 46285 | B142: Sunshine Coast | C142: 1 | D142: 1 | E142: On The Clock | F142: Bet | G142: Bet | H142: 8 | I142: 10 | J142: 0.025 | K142: 1 | L142: 5 | M142: Loss | N142: =IF(M142="Win",IF(F142="Bet",(I142-1)*K142,K142),IF(M142="Loss",IF(F142="Bet",-K142,-(I142-1)*K142),IF(M142="Void",0,""))) | O142: =IF(OR(M142="Win",M142="Loss"),IF(F142="Bet",K142,(I142-1)*K142),"")
A143: 46285 | B143: Sunshine Coast | C143: 1 | D143: 6 | E143: Chat Mignon | F143: Bet | G143: Bet | H143: 9.4 | I143: 14.99 | J143: 0.0235 | K143: 1 | L143: 3 | M143: Loss | N143: =IF(M143="Win",IF(F143="Bet",(I143-1)*K143,K143),IF(M143="Loss",IF(F143="Bet",-K143,-(I143-1)*K143),IF(M143="Void",0,""))) | O143: =IF(OR(M143="Win",M143="Loss"),IF(F143="Bet",K143,(I143-1)*K143),"")
A144: 46285 | B144: Mount Gambier | C144: 7 | D144: 7 | E144: Forever Waiting | F144: Bet | G144: Bet | H144: 4.4 | I144: 6 | J144: 0.0201 | K144: 1 | L144: 4 | M144: Loss | N144: =IF(M144="Win",IF(F144="Bet",(I144-1)*K144,K144),IF(M144="Loss",IF(F144="Bet",-K144,-(I144-1)*K144),IF(M144="Void",0,""))) | O144: =IF(OR(M144="Win",M144="Loss"),IF(F144="Bet",K144,(I144-1)*K144),"")
A145: 46285 | B145: Nowra | C145: 6 | D145: 9 | E145: Battle Warrior | F145: Bet | G145: Bet | H145: 8.3 | I145: 11 | J145: 0.0203 | K145: 1 | L145: 6 | M145: Loss | N145: =IF(M145="Win",IF(F145="Bet",(I145-1)*K145,K145),IF(M145="Loss",IF(F145="Bet",-K145,-(I145-1)*K145),IF(M145="Void",0,""))) | O145: =IF(OR(M145="Win",M145="Loss"),IF(F145="Bet",K145,(I145-1)*K145),"")
A146: 46285 | B146: Sunshine Coast | C146: 3 | D146: 6 | E146: Shedrivesabentley | F146: Bet | G146: Bet | H146: 7.8 | I146: 9.5 | J146: 0.0226 | K146: 1 | L146: 6 | M146: Loss | N146: =IF(M146="Win",IF(F146="Bet",(I146-1)*K146,K146),IF(M146="Loss",IF(F146="Bet",-K146,-(I146-1)*K146),IF(M146="Void",0,""))) | O146: =IF(OR(M146="Win",M146="Loss"),IF(F146="Bet",K146,(I146-1)*K146),"")
A147: 46285 | B147: Bairnsdale | C147: 2 | D147: 14 | E147: Kooralbyn | F147: Bet | G147: Bet | H147: 5.9 | I147: 7.6 | J147: 0.0223 | K147: 1 | L147: 1 | M147: Win | N147: =IF(M147="Win",IF(F147="Bet",(I147-1)*K147,K147),IF(M147="Loss",IF(F147="Bet",-K147,-(I147-1)*K147),IF(M147="Void",0,""))) | O147: =IF(OR(M147="Win",M147="Loss"),IF(F147="Bet",K147,(I147-1)*K147),"")
A148: 46285 | B148: Bairnsdale | C148: 5 | D148: 10 | E148: Discobay | F148: Bet | G148: Bet | H148: 9 | I148: 11 | J148: 0.0207 | K148: 1 | L148: 4 | M148: Loss | N148: =IF(M148="Win",IF(F148="Bet",(I148-1)*K148,K148),IF(M148="Loss",IF(F148="Bet",-K148,-(I148-1)*K148),IF(M148="Void",0,""))) | O148: =IF(OR(M148="Win",M148="Loss"),IF(F148="Bet",K148,(I148-1)*K148),"")
A149: 46285 | B149: Mount Gambier | C149: 5 | D149: 6 | E149: Salsbury Hill | F149: Bet | G149: Bet | H149: 9.6 | I149: 15 | J149: 0.0204 | K149: 1 | L149: 5 | M149: Loss | N149: =IF(M149="Win",IF(F149="Bet",(I149-1)*K149,K149),IF(M149="Loss",IF(F149="Bet",-K149,-(I149-1)*K149),IF(M149="Void",0,""))) | O149: =IF(OR(M149="Win",M149="Loss"),IF(F149="Bet",K149,(I149-1)*K149),"")
A150: 46285 | B150: Mount Gambier | C150: 6 | D150: 1 | E150: Farag | F150: Bet | G150: Bet | H150: 10.3 | I150: 13 | J150: 0.02 | K150: 1 | L150: 6 | M150: Loss | N150: =IF(M150="Win",IF(F150="Bet",(I150-1)*K150,K150),IF(M150="Loss",IF(F150="Bet",-K150,-(I150-1)*K150),IF(M150="Void",0,""))) | O150: =IF(OR(M150="Win",M150="Loss"),IF(F150="Bet",K150,(I150-1)*K150),"")
A151: 46286 | B151: Narromine | C151: 3 | D151: 4 | E151: The Beast | F151: Bet | G151: Prime | H151: 3.3 | I151: 3.7 | J151: 0.0286 | K151: 1 | L151: 2 | M151: Loss | N151: =IF(M151="Win",IF(F151="Bet",(I151-1)*K151,K151),IF(M151="Loss",IF(F151="Bet",-K151,-(I151-1)*K151),IF(M151="Void",0,""))) | O151: =IF(OR(M151="Win",M151="Loss"),IF(F151="Bet",K151,(I151-1)*K151),"")
A152: 46286 | B152: Warrnambool | C152: 4 | D152: 2 | E152: It's A Yes | F152: Bet | G152: Prime | H152: 2.15 | I152: 2.22 | J152: -0.0012 | K152: 1 | L152: 2 | M152: Loss | N152: =IF(M152="Win",IF(F152="Bet",(I152-1)*K152,K152),IF(M152="Loss",IF(F152="Bet",-K152,-(I152-1)*K152),IF(M152="Void",0,""))) | O152: =IF(OR(M152="Win",M152="Loss"),IF(F152="Bet",K152,(I152-1)*K152),"")
A153: 46286 | B153: Warrnambool | C153: 7 | D153: 2 | E153: Magnetic Chess | F153: Bet | G153: Bet | H153: 2.6 | I153: 2.4 | J153: -0.0482 | K153: 1 | L153: 8 | M153: Loss | N153: =IF(M153="Win",IF(F153="Bet",(I153-1)*K153,K153),IF(M153="Loss",IF(F153="Bet",-K153,-(I153-1)*K153),IF(M153="Void",0,""))) | O153: =IF(OR(M153="Win",M153="Loss"),IF(F153="Bet",K153,(I153-1)*K153),"")
... A162: 46287 | B162: Leeton | C162: 7 | D162: 6 | E162: Justbetryin' | F162: Bet | G162: Bet | H162: 6.8 | I162: 11.43 | J162: 0.0225 | K162: 1 | L162: 1 | M162: Win | N162: =IF(M162="Win",IF(F162="Bet",(I162-1)*K162,K162),IF(M162="Loss",IF(F162="Bet",-K162,-(I162-1)*K162),IF(M162="Void",0,""))) | O162: =IF(OR(M162="Win",M162="Loss"),IF(F162="Bet",K162,(I162-1)*K162),"")
A163: 46288 | B163: Geelong | C163: 1 | D163: 9 | E163: Youmzaa | F163: Bet | G163: Bet | H163: 1.6 | I163: 1.65 | J163: 0.0265 | K163: 1 | M163: Void | N163: =IF(M163="Win",IF(F163="Bet",(I163-1)*K163,K163),IF(M163="Loss",IF(F163="Bet",-K163,-(I163-1)*K163),IF(M163="Void",0,""))) | O163: =IF(OR(M163="Win",M163="Loss"),IF(F163="Bet",K163,(I163-1)*K163),"")
A164: 46288 | B164: Eagle Farm | C164: 3 | D164: 1 | E164: Breezin' | F164: Bet | G164: Bet | H164: 7.3 | I164: 9.5 | J164: 0.0254 | K164: 1 | L164: 6 | M164: Loss | N164: =IF(M164="Win",IF(F164="Bet",(I164-1)*K164,K164),IF(M164="Loss",IF(F164="Bet",-K164,-(I164-1)*K164),IF(M164="Void",0,""))) | O164: =IF(OR(M164="Win",M164="Loss"),IF(F164="Bet",K164,(I164-1)*K164),"")
A165: 46288 | B165: Eagle Farm | C165: 7 | D165: 15 | E165: Lady Windermere | F165: Bet | G165: Bet | H165: 8 | I165: 9.5 | J165: 0.0204 | K165: 1 | L165: 7 | M165: Loss | N165: =IF(M165="Win",IF(F165="Bet",(I165-1)*K165,K165),IF(M165="Loss",IF(F165="Bet",-K165,-(I165-1)*K165),IF(M165="Void",0,""))) | O165: =IF(OR(M165="Win",M165="Loss"),IF(F165="Bet",K165,(I165-1)*K165),"")
A166: 46288 | B166: Geelong | C166: 6 | D166: 3 | E166: Shultzy | F166: Bet | G166: Bet | H166: 6 | I166: 7 | J166: 0.024 | K166: 1 | M166: Void | N166: =IF(M166="Win",IF(F166="Bet",(I166-1)*K166,K166),IF(M166="Loss",IF(F166="Bet",-K166,-(I166-1)*K166),IF(M166="Void",0,""))) | O166: =IF(OR(M166="Win",M166="Loss"),IF(F166="Bet",K166,(I166-1)*K166),"")
A167: 46288 | B167: Geelong | C167: 3 | D167: 3 | E167: Fringilla | F167: Bet | G167: Bet | H167: 4 | I167: 4.4 | J167: 0.0205 | K167: 1 | L167: 2 | M167: Loss | N167: =IF(M167="Win",IF(F167="Bet",(I167-1)*K167,K167),IF(M167="Loss",IF(F167="Bet",-K167,-(I167-1)*K167),IF(M167="Void",0,""))) | O167: =IF(OR(M167="Win",M167="Loss"),IF(F167="Bet",K167,(I167-1)*K167),"")
A168: 46288 | B168: Warwick Farm | C168: 7 | D168: 10 | E168: Agatha | F168: Bet | G168: Bet | H168: 3.3 | I168: 4.31 | J168: 0.0388 | K168: 1 | L168: 3 | M168: Loss | N168: =IF(M168="Win",IF(F168="Bet",(I168-1)*K168,K168),IF(M168="Loss",IF(F168="Bet",-K168,-(I168-1)*K168),IF(M168="Void",0,""))) | O168: =IF(OR(M168="Win",M168="Loss"),IF(F168="Bet",K168,(I168-1)*K168),"")
A169: 46288 | B169: Warwick Farm | C169: 6 | D169: 6 | E169: Call Me Gorgeous | F169: Bet | G169: Bet | H169: 5.7 | I169: 6.5 | J169: 0.0218 | K169: 1 | L169: 7 | M169: Loss | N169: =IF(M169="Win",IF(F169="Bet",(I169-1)*K169,K169),IF(M169="Loss",IF(F169="Bet",-K169,-(I169-1)*K169),IF(M169="Void",0,""))) | O169: =IF(OR(M169="Win",M169="Loss"),IF(F169="Bet",K169,(I169-1)*K169),"")
A170: 46288 | B170: Eagle Farm | C170: 4 | D170: 6 | E170: Anderlay | F170: Bet | G170: Bet | H170: 6.5 | I170: 10 | J170: 0.0216 | K170: 1 | L170: 5 | M170: Loss | N170: =IF(M170="Win",IF(F170="Bet",(I170-1)*K170,K170),IF(M170="Loss",IF(F170="Bet",-K170,-(I170-1)*K170),IF(M170="Void",0,""))) | O170: =IF(OR(M170="Win",M170="Loss"),IF(F170="Bet",K170,(I170-1)*K170),"")
A171: 46288 | B171: Northam | C171: 8 | D171: 1 | E171: Hey True Blue | F171: Bet | G171: Bet | H171: 6.9 | I171: 17 | J171: 0.0201 | K171: 1 | L171: 7 | M171: Loss | N171: =IF(M171="Win",IF(F171="Bet",(I171-1)*K171,K171),IF(M171="Loss",IF(F171="Bet",-K171,-(I171-1)*K171),IF(M171="Void",0,""))) | O171: =IF(OR(M171="Win",M171="Loss"),IF(F171="Bet",K171,(I171-1)*K171),"")
A172: 46288 | B172: Eagle Farm | C172: 6 | D172: 5 | E172: Fireforce | F172: Bet | G172: Bet | H172: 7.9 | I172: 9.5 | J172: 0.0206 | K172: 1 | L172: 8 | M172: Loss | N172: =IF(M172="Win",IF(F172="Bet",(I172-1)*K172,K172),IF(M172="Loss",IF(F172="Bet",-K172,-(I172-1)*K172),IF(M172="Void",0,""))) | O172: =IF(OR(M172="Win",M172="Loss"),IF(F172="Bet",K172,(I172-1)*K172),"")
A173: 46288 | B173: Northam | C173: 5 | D173: 8 | E173: The Stalagmite | F173: Bet | G173: Bet | H173: 7.7 | I173: 9.5 | J173: 0.0247 | K173: 1 | L173: 12 | M173: Loss | N173: =IF(M173="Win",IF(F173="Bet",(I173-1)*K173,K173),IF(M173="Loss",IF(F173="Bet",-K173,-(I173-1)*K173),IF(M173="Void",0,""))) | O173: =IF(OR(M173="Win",M173="Loss"),IF(F173="Bet",K173,(I173-1)*K173),"")
A174: 46288 | B174: Eagle Farm | C174: 4 | D174: 8 | E174: Buttercup | F174: Bet | G174: Bet | H174: 4.2 | I174: 6.89 | J174: 0.0217 | K174: 1 | L174: 3 | M174: Loss | N174: =IF(M174="Win",IF(F174="Bet",(I174-1)*K174,K174),IF(M174="Loss",IF(F174="Bet",-K174,-(I174-1)*K174),IF(M174="Void",0,""))) | O174: =IF(OR(M174="Win",M174="Loss"),IF(F174="Bet",K174,(I174-1)*K174),"")
...

Sheet Lays
O2: Lays
O3: Every lay, 11 Sep to 2 Oct 2026
A5: Date | B5: Track | C5: Race | D5: No. | E5: Horse | F5: Call | G5: Tag | H5: Rated $ | I5: Price $ | J5: Edge | K5: Stake (u) | L5: Finish | M5: Result | N5: Profit (u) | O5: At risk (u)
A6: 46276 | B6: Geelong | C6: 6 | D6: 10 | E6: Karren | F6: Lay | G6: Lay | H6: 2.85 | I6: 1.98 | J6: -0.1505 | K6: 1 | L6: 2 | M6: Win | N6: =IF(M6="Win",IF(F6="Bet",(I6-1)*K6,K6),IF(M6="Loss",IF(F6="Bet",-K6,-(I6-1)*K6),IF(M6="Void",0,""))) | O6: =IF(OR(M6="Win",M6="Loss"),IF(F6="Bet",K6,(I6-1)*K6),"")
A7: 46276 | B7: Bordertown | C7: 1 | D7: 6 | E7: Gradivus | F7: Lay | G7: Lay | H7: 4.9 | I7: 3.3 | J7: -0.1004 | K7: 1 | L7: 4 | M7: Win | N7: =IF(M7="Win",IF(F7="Bet",(I7-1)*K7,K7),IF(M7="Loss",IF(F7="Bet",-K7,-(I7-1)*K7),IF(M7="Void",0,""))) | O7: =IF(OR(M7="Win",M7="Loss"),IF(F7="Bet",K7,(I7-1)*K7),"")
A8: 46276 | B8: Tuncurry | C8: 3 | D8: 1 | E8: Sea Level | F8: Lay | G8: Lay | H8: 2.25 | I8: 1.75 | J8: -0.1224 | K8: 1 | L8: 1 | M8: Loss | N8: =IF(M8="Win",IF(F8="Bet",(I8-1)*K8,K8),IF(M8="Loss",IF(F8="Bet",-K8,-(I8-1)*K8),IF(M8="Void",0,""))) | O8: =IF(OR(M8="Win",M8="Loss"),IF(F8="Bet",K8,(I8-1)*K8),"")
A9: 46276 | B9: Tuncurry | C9: 8 | D9: 13 | E9: Andrea | F9: Lay | G9: Lay | H9: 2.35 | I9: 1.75 | J9: -0.144 | K9: 1 | L9: 1 | M9: Loss | N9: =IF(M9="Win",IF(F9="Bet",(I9-1)*K9,K9),IF(M9="Loss",IF(F9="Bet",-K9,-(I9-1)*K9),IF(M9="Void",0,""))) | O9: =IF(OR(M9="Win",M9="Loss"),IF(F9="Bet",K9,(I9-1)*K9),"")
A10: 46276 | B10: Goulburn | C10: 2 | D10: 6 | E10: Spain | F10: Lay | G10: Lay | H10: 1.65 | I10: 1.35 | J10: -0.1291 | K10: 1 | L10: 1 | M10: Loss | N10: =IF(M10="Win",IF(F10="Bet",(I10-1)*K10,K10),IF(M10="Loss",IF(F10="Bet",-K10,-(I10-1)*K10),IF(M10="Void",0,""))) | O10: =IF(OR(M10="Win",M10="Loss"),IF(F10="Bet",K10,(I10-1)*K10),"")
A11: 46276 | B11: Goulburn | C11: 3 | D11: 10 | E11: Montresor | F11: Lay | G11: Lay | H11: 2.4 | I11: 1.83 | J11: -0.1254 | K11: 1 | L11: 2 | M11: Win | N11: =IF(M11="Win",IF(F11="Bet",(I11-1)*K11,K11),IF(M11="Loss",IF(F11="Bet",-K11,-(I11-1)*K11),IF(M11="Void",0,""))) | O11: =IF(OR(M11="Win",M11="Loss"),IF(F11="Bet",K11,(I11-1)*K11),"")
A12: 46276 | B12: Sunshine Coast | C12: 1 | D12: 5 | E12: Amelioration | F12: Lay | G12: Lay | H12: 3 | I12: 2.25 | J12: -0.1152 | K12: 1 | L12: 3 | M12: Win | N12: =IF(M12="Win",IF(F12="Bet",(I12-1)*K12,K12),IF(M12="Loss",IF(F12="Bet",-K12,-(I12-1)*K12),IF(M12="Void",0,""))) | O12: =IF(OR(M12="Win",M12="Loss"),IF(F12="Bet",K12,(I12-1)*K12),"")
A13: 46277 | B13: Morphettville | C13: 4 | D13: 13 | E13: Harmonic Dancer | F13: Lay | G13: Lay | H13: 3.2 | I13: 1.73 | J13: -0.1087 | K13: 1 | L13: 3 | M13: Win | N13: =IF(M13="Win",IF(F13="Bet",(I13-1)*K13,K13),IF(M13="Loss",IF(F13="Bet",-K13,-(I13-1)*K13),IF(M13="Void",0,""))) | O13: =IF(OR(M13="Win",M13="Loss"),IF(F13="Bet",K13,(I13-1)*K13),"")
A14: 46277 | B14: Morphettville | C14: 6 | D14: 7 | E14: You Sexy Thing | F14: Lay | G14: Lay | H14: 3.8 | I14: 2.5 | J14: -0.1372 | K14: 1 | L14: 2 | M14: Win | N14: =IF(M14="Win",IF(F14="Bet",(I14-1)*K14,K14),IF(M14="Loss",IF(F14="Bet",-K14,-(I14-1)*K14),IF(M14="Void",0,""))) | O14: =IF(OR(M14="Win",M14="Loss"),IF(F14="Bet",K14,(I14-1)*K14),"")
A15: 46277 | B15: Flemington | C15: 6 | D15: 8 | E15: Sass Appeal | F15: Lay | G15: Lay | H15: 5.5 | I15: 3.4 | J15: -0.1121 | K15: 1 | L15: 4 | M15: Win | N15: =IF(M15="Win",IF(F15="Bet",(I15-1)*K15,K15),IF(M15="Loss",IF(F15="Bet",-K15,-(I15-1)*K15),IF(M15="Void",0,""))) | O15: =IF(OR(M15="Win",M15="Loss"),IF(F15="Bet",K15,(I15-1)*K15),"")
A16: 46277 | B16: Flemington | C16: 7 | D16: 5 | E16: Oliveanotherday | F16: Lay | G16: Lay | H16: 2.45 | I16: 1.65 | J16: -0.1955 | K16: 1 | L16: 5 | M16: Win | N16: =IF(M16="Win",IF(F16="Bet",(I16-1)*K16,K16),IF(M16="Loss",IF(F16="Bet",-K16,-(I16-1)*K16),IF(M16="Void",0,""))) | O16: =IF(OR(M16="Win",M16="Loss"),IF(F16="Bet",K16,(I16-1)*K16),"")
A17: 46277 | B17: Flemington | C17: 8 | D17: 12 | E17: Sheza Alibi | F17: Lay | G17: Lay | H17: 2.1 | I17: 1.65 | J17: -0.1263 | K17: 1 | L17: 1 | M17: Loss | N17: =IF(M17="Win",IF(F17="Bet",(I17-1)*K17,K17),IF(M17="Loss",IF(F17="Bet",-K17,-(I17-1)*K17),IF(M17="Void",0,""))) | O17: =IF(OR(M17="Win",M17="Loss"),IF(F17="Bet",K17,(I17-1)*K17),"")
... A42: 46277 | B42: Alice Springs | C42: 5 | D42: 5 | E42: Mummsie | F42: Lay | G42: Lay | H42: 5 | I42: 3.2 | J42: -0.1117 | K42: 1 | L42: 1 | M42: Loss | N42: =IF(M42="Win",IF(F42="Bet",(I42-1)*K42,K42),IF(M42="Loss",IF(F42="Bet",-K42,-(I42-1)*K42),IF(M42="Void",0,""))) | O42: =IF(OR(M42="Win",M42="Loss"),IF(F42="Bet",K42,(I42-1)*K42),"")
A43: 46277 | B43: Toowoomba | C43: 1 | D43: 11 | E43: Crypto Miss | F43: Lay | G43: Lay | H43: 4.3 | I43: 2.8 | J43: -0.1219 | K43: 1 | L43: Unplaced | M43: Win | N43: =IF(M43="Win",IF(F43="Bet",(I43-1)*K43,K43),IF(M43="Loss",IF(F43="Bet",-K43,-(I43-1)*K43),IF(M43="Void",0,""))) | O43: =IF(OR(M43="Win",M43="Loss"),IF(F43="Bet",K43,(I43-1)*K43),"")
A44: 46278 | B44: Dalby | C44: 4 | D44: 6 | E44: Lady Willpower | F44: Lay | G44: Lay | H44: 1.45 | I44: 1.22 | J44: -0.1281 | K44: 1 | L44: 1 | M44: Loss | N44: =IF(M44="Win",IF(F44="Bet",(I44-1)*K44,K44),IF(M44="Loss",IF(F44="Bet",-K44,-(I44-1)*K44),IF(M44="Void",0,""))) | O44: =IF(OR(M44="Win",M44="Loss"),IF(F44="Bet",K44,(I44-1)*K44),"")
A45: 46278 | B45: Dalby | C45: 6 | D45: 4 | E45: Solo Hunter | F45: Lay | G45: Lay | H45: 1.7 | I45: 1.4 | J45: -0.1297 | K45: 1 | L45: 1 | M45: Loss | N45: =IF(M45="Win",IF(F45="Bet",(I45-1)*K45,K45),IF(M45="Loss",IF(F45="Bet",-K45,-(I45-1)*K45),IF(M45="Void",0,""))) | O45: =IF(OR(M45="Win",M45="Loss"),IF(F45="Bet",K45,(I45-1)*K45),"")
A46: 46278 | B46: Dalby | C46: 8 | D46: 8 | E46: Snugg | F46: Lay | G46: Lay | H46: 3.5 | I46: 2.6 | J46: -0.0974 | K46: 1 | L46: 3 | M46: Win | N46: =IF(M46="Win",IF(F46="Bet",(I46-1)*K46,K46),IF(M46="Loss",IF(F46="Bet",-K46,-(I46-1)*K46),IF(M46="Void",0,""))) | O46: =IF(OR(M46="Win",M46="Loss"),IF(F46="Bet",K46,(I46-1)*K46),"")
A47: 46278 | B47: Sale | C47: 1 | D47: 4 | E47: Mr Margolin | F47: Lay | G47: Lay | H47: 5.8 | I47: 3.7 | J47: -0.0966 | K47: 1 | L47: 1 | M47: Loss | N47: =IF(M47="Win",IF(F47="Bet",(I47-1)*K47,K47),IF(M47="Loss",IF(F47="Bet",-K47,-(I47-1)*K47),IF(M47="Void",0,""))) | O47: =IF(OR(M47="Win",M47="Loss"),IF(F47="Bet",K47,(I47-1)*K47),"")
A48: 46278 | B48: Sale | C48: 3 | D48: 12 | E48: Zendarina | F48: Lay | G48: Lay | H48: 3.7 | I48: 2.7 | J48: -0.0974 | K48: 1 | L48: 1 | M48: Loss | N48: =IF(M48="Win",IF(F48="Bet",(I48-1)*K48,K48),IF(M48="Loss",IF(F48="Bet",-K48,-(I48-1)*K48),IF(M48="Void",0,""))) | O48: =IF(OR(M48="Win",M48="Loss"),IF(F48="Bet",K48,(I48-1)*K48),"")
A49: 46278 | B49: Sale | C49: 4 | D49: 12 | E49: Classic Secret | F49: Lay | G49: Lay | H49: 3.5 | I49: 2.75 | J49: -0.0759 | K49: 1 | L49: 10 | M49: Win | N49: =IF(M49="Win",IF(F49="Bet",(I49-1)*K49,K49),IF(M49="Loss",IF(F49="Bet",-K49,-(I49-1)*K49),IF(M49="Void",0,""))) | O49: =IF(OR(M49="Win",M49="Loss"),IF(F49="Bet",K49,(I49-1)*K49),"")
A50: 46278 | B50: Coffs Harbour | C50: 3 | D50: 10 | E50: Magic Snitzel | F50: Lay | G50: Lay | H50: 3.1 | I50: 2.26 | J50: -0.0605 | K50: 1 | L50: 4 | M50: Win | N50: =IF(M50="Win",IF(F50="Bet",(I50-1)*K50,K50),IF(M50="Loss",IF(F50="Bet",-K50,-(I50-1)*K50),IF(M50="Void",0,""))) | O50: =IF(OR(M50="Win",M50="Loss"),IF(F50="Bet",K50,(I50-1)*K50),"")
A51: 46278 | B51: Coffs Harbour | C51: 7 | D51: 5 | E51: Jade Trees | F51: Lay | G51: Lay | H51: 2.35 | I51: 1.7 | J51: -0.1654 | K51: 1 | L51: 1 | M51: Loss | N51: =IF(M51="Win",IF(F51="Bet",(I51-1)*K51,K51),IF(M51="Loss",IF(F51="Bet",-K51,-(I51-1)*K51),IF(M51="Void",0,""))) | O51: =IF(OR(M51="Win",M51="Loss"),IF(F51="Bet",K51,(I51-1)*K51),"")
A52: 46278 | B52: Bathurst | C52: 1 | D52: 10 | E52: May The Force | F52: Lay | G52: Lay | H52: 3.9 | I52: 2.8 | J52: -0.0996 | K52: 1 | L52: 1 | M52: Loss | N52: =IF(M52="Win",IF(F52="Bet",(I52-1)*K52,K52),IF(M52="Loss",IF(F52="Bet",-K52,-(I52-1)*K52),IF(M52="Void",0,""))) | O52: =IF(OR(M52="Win",M52="Loss"),IF(F52="Bet",K52,(I52-1)*K52),"")
A53: 46278 | B53: Bathurst | C53: 5 | D53: 1 | E53: Inquiring Minds | F53: Lay | G53: Lay | H53: 4.8 | I53: 3.3 | J53: -0.0935 | K53: 1 | L53: 2 | M53: Win | N53: =IF(M53="Win",IF(F53="Bet",(I53-1)*K53,K53),IF(M53="Loss",IF(F53="Bet",-K53,-(I53-1)*K53),IF(M53="Void",0,""))) | O53: =IF(OR(M53="Win",M53="Loss"),IF(F53="Bet",K53,(I53-1)*K53),"")
A54: 46278 | B54: Bathurst | C54: 6 | D54: 16 | E54: Tom Vegas | F54: Lay | G54: Lay | H54: 5.7 | I54: 3.4 | J54: -0.1194 | K54: 1 | L54: 2 | M54: Win | N54: =IF(M54="Win",IF(F54="Bet",(I54-1)*K54,K54),IF(M54="Loss",IF(F54="Bet",-K54,-(I54-1)*K54),IF(M54="Void",0,""))) | O54: =IF(OR(M54="Win",M54="Loss"),IF(F54="Bet",K54,(I54-1)*K54),"")
A55: 46278 | B55: Dalby | C55: 3 | D55: 4 | E55: Royal Diplomat | F55: Lay | G55: Lay | H55: 2.35 | I55: 2.05 | J55: -0.0632 | K55: 1 | L55: 1 | M55: Loss | N55: =IF(M55="Win",IF(F55="Bet",(I55-1)*K55,K55),IF(M55="Loss",IF(F55="Bet",-K55,-(I55-1)*K55),IF(M55="Void",0,""))) | O55: =IF(OR(M55="Win",M55="Loss"),IF(F55="Bet",K55,(I55-1)*K55),"")
... A94: 46281 | B94: Belmont | C94: 7 | D94: 5 | E94: Vampi Queen | F94: Lay | G94: Lay | H94: 6 | I94: 2.5 | J94: -0.1913 | K94: 1 | L94: 1 | M94: Loss | N94: =IF(M94="Win",IF(F94="Bet",(I94-1)*K94,K94),IF(M94="Loss",IF(F94="Bet",-K94,-(I94-1)*K94),IF(M94="Void",0,""))) | O94: =IF(OR(M94="Win",M94="Loss"),IF(F94="Bet",K94,(I94-1)*K94),"")
A95: 46281 | B95: Canterbury | C95: 4 | D95: 8 | E95: Ertijaaj | F95: Lay | G95: Lay | H95: 10.4 | I95: 4.2 | J95: -0.1417 | K95: 1 | M95: Void | N95: =IF(M95="Win",IF(F95="Bet",(I95-1)*K95,K95),IF(M95="Loss",IF(F95="Bet",-K95,-(I95-1)*K95),IF(M95="Void",0,""))) | O95: =IF(OR(M95="Win",M95="Loss"),IF(F95="Bet",K95,(I95-1)*K95),"")
A96: 46281 | B96: Launceston | C96: 6 | D96: 3 | E96: Vinraam | F96: Lay | G96: Lay | H96: 7.1 | I96: 3.4 | J96: -0.1535 | K96: 1 | L96: 5 | M96: Win | N96: =IF(M96="Win",IF(F96="Bet",(I96-1)*K96,K96),IF(M96="Loss",IF(F96="Bet",-K96,-(I96-1)*K96),IF(M96="Void",0,""))) | O96: =IF(OR(M96="Win",M96="Loss"),IF(F96="Bet",K96,(I96-1)*K96),"")
A97: 46281 | B97: Launceston | C97: 6 | D97: 2 | E97: Bailed | F97: Lay | G97: Lay | H97: 5.5 | I97: 2.6 | J97: -0.1627 | K97: 1 | L97: 3 | M97: Win | N97: =IF(M97="Win",IF(F97="Bet",(I97-1)*K97,K97),IF(M97="Loss",IF(F97="Bet",-K97,-(I97-1)*K97),IF(M97="Void",0,""))) | O97: =IF(OR(M97="Win",M97="Loss"),IF(F97="Bet",K97,(I97-1)*K97),"")
A98: 46281 | B98: Balaklava | C98: 8 | D98: 8 | E98: Embellisher | F98: Lay | G98: Lay | H98: 7.3 | I98: 3.1 | J98: -0.1494 | K98: 1 | L98: 4 | M98: Win | N98: =IF(M98="Win",IF(F98="Bet",(I98-1)*K98,K98),IF(M98="Loss",IF(F98="Bet",-K98,-(I98-1)*K98),IF(M98="Void",0,""))) | O98: =IF(OR(M98="Win",M98="Loss"),IF(F98="Bet",K98,(I98-1)*K98),"")
A99: 46281 | B99: Belmont | C99: 6 | D99: 7 | E99: Streamlined | F99: Lay | G99: Lay | H99: 3.1 | I99: 2.25 | J99: -0.1047 | K99: 1 | L99: 1 | M99: Loss | N99: =IF(M99="Win",IF(F99="Bet",(I99-1)*K99,K99),IF(M99="Loss",IF(F99="Bet",-K99,-(I99-1)*K99),IF(M99="Void",0,""))) | O99: =IF(OR(M99="Win",M99="Loss"),IF(F99="Bet",K99,(I99-1)*K99),"")
A100: 46281 | B100: Doomben | C100: 5 | D100: 1 | E100: Global Eclipse | F100: Lay | G100: Lay | H100: 4 | I100: 2.9 | J100: -0.1072 | K100: 1 | L100: 1 | M100: Loss | N100: =IF(M100="Win",IF(F100="Bet",(I100-1)*K100,K100),IF(M100="Loss",IF(F100="Bet",-K100,-(I100-1)*K100),IF(M100="Void",0,""))) | O100: =IF(OR(M100="Win",M100="Loss"),IF(F100="Bet",K100,(I100-1)*K100),"")
A101: 46281 | B101: Doomben | C101: 6 | D101: 4 | E101: Lockyer | F101: Lay | G101: Lay | H101: 3.1 | I101: 2.25 | J101: -0.107 | K101: 1 | L101: 1 | M101: Loss | N101: =IF(M101="Win",IF(F101="Bet",(I101-1)*K101,K101),IF(M101="Loss",IF(F101="Bet",-K101,-(I101-1)*K101),IF(M101="Void",0,""))) | O101: =IF(OR(M101="Win",M101="Loss"),IF(F101="Bet",K101,(I101-1)*K101),"")
A102: 46281 | B102: Balaklava | C102: 10 | D102: 3 | E102: Uptown Monk | F102: Lay | G102: Lay | H102: 3.7 | I102: 2.4 | J102: -0.1074 | K102: 1 | L102: 1 | M102: Loss | N102: =IF(M102="Win",IF(F102="Bet",(I102-1)*K102,K102),IF(M102="Loss",IF(F102="Bet",-K102,-(I102-1)*K102),IF(M102="Void",0,""))) | O102: =IF(OR(M102="Win",M102="Loss"),IF(F102="Bet",K102,(I102-1)*K102),"")
A103: 46281 | B103: Canterbury | C103: 5 | D103: 8 | E103: Whatalegacy | F103: Lay | G103: Lay | H103: 2.85 | I103: 2.1 | J103: -0.1223 | K103: 1 | L103: 1 | M103: Loss | N103: =IF(M103="Win",IF(F103="Bet",(I103-1)*K103,K103),IF(M103="Loss",IF(F103="Bet",-K103,-(I103-1)*K103),IF(M103="Void",0,""))) | O103: =IF(OR(M103="Win",M103="Loss"),IF(F103="Bet",K103,(I103-1)*K103),"")
A104: 46282 | B104: Mornington | C104: 2 | D104: 4 | E104: Top Conti | F104: Lay | G104: Lay | H104: 2.45 | I104: 1.74 | J104: -0.1485 | K104: 1 | L104: 1 | M104: Loss | N104: =IF(M104="Win",IF(F104="Bet",(I104-1)*K104,K104),IF(M104="Loss",IF(F104="Bet",-K104,-(I104-1)*K104),IF(M104="Void",0,""))) | O104: =IF(OR(M104="Win",M104="Loss"),IF(F104="Bet",K104,(I104-1)*K104),"")
A105: 46282 | B105: Illawarra Grange | C105: 2 | D105: 6 | E105: Slander | F105: Lay | G105: Lay | H105: 3.3 | I105: 1.82 | J105: -0.1331 | K105: 1 | L105: 1 | M105: Loss | N105: =IF(M105="Win",IF(F105="Bet",(I105-1)*K105,K105),IF(M105="Loss",IF(F105="Bet",-K105,-(I105-1)*K105),IF(M105="Void",0,""))) | O105: =IF(OR(M105="Win",M105="Loss"),IF(F105="Bet",K105,(I105-1)*K105),"")
A106: 46282 | B106: Bunbury | C106: 5 | D106: 7 | E106: Poppy's Roses | F106: Lay | G106: Lay | H106: 2.65 | I106: 2.2 | J106: -0.1607 | K106: 1 | L106: 3 | M106: Win | N106: =IF(M106="Win",IF(F106="Bet",(I106-1)*K106,K106),IF(M106="Loss",IF(F106="Bet",-K106,-(I106-1)*K106),IF(M106="Void",0,""))) | O106: =IF(OR(M106="Win",M106="Loss"),IF(F106="Bet",K106,(I106-1)*K106),"")
A107: 46282 | B107: Bunbury | C107: 8 | D107: 11 | E107: Return Of The Mach | F107: Lay | G107: Lay | H107: 5.5 | I107: 2.96 | J107: -0.1107 | K107: 1 | L107: 2 | M107: Win | N107: =IF(M107="Win",IF(F107="Bet",(I107-1)*K107,K107),IF(M107="Loss",IF(F107="Bet",-K107,-(I107-1)*K107),IF(M107="Void",0,""))) | O107: =IF(OR(M107="Win",M107="Loss"),IF(F107="Bet",K107,(I107-1)*K107),"")
... A109: 46282 | B109: Beaudesert | C109: 1 | D109: 8 | E109: Wasai | F109: Lay | G109: Lay | H109: 2.35 | I109: 1.75 | J109: -0.1418 | K109: 1 | L109: 3 | M109: Win | N109: =IF(M109="Win",IF(F109="Bet",(I109-1)*K109,K109),IF(M109="Loss",IF(F109="Bet",-K109,-(I109-1)*K109),IF(M109="Void",0,""))) | O109: =IF(OR(M109="Win",M109="Loss"),IF(F109="Bet",K109,(I109-1)*K109),"")
A110: 46282 | B110: Mornington | C110: 7 | D110: 8 | E110: Justique | F110: Lay | G110: Lay | H110: 7.6 | I110: 4.2 | J110: -0.1063 | K110: 1 | M110: Void | N110: =IF(M110="Win",IF(F110="Bet",(I110-1)*K110,K110),IF(M110="Loss",IF(F110="Bet",-K110,-(I110-1)*K110),IF(M110="Void",0,""))) | O110: =IF(OR(M110="Win",M110="Loss"),IF(F110="Bet",K110,(I110-1)*K110),"")
A111: 46282 | B111: Mornington | C111: 1 | D111: 11 | E111: Adakite | F111: Lay | G111: Lay | H111: 3.4 | I111: 2.15 | J111: -0.122 | K111: 1 | L111: 2 | M111: Win | N111: =IF(M111="Win",IF(F111="Bet",(I111-1)*K111,K111),IF(M111="Loss",IF(F111="Bet",-K111,-(I111-1)*K111),IF(M111="Void",0,""))) | O111: =IF(OR(M111="Win",M111="Loss"),IF(F111="Bet",K111,(I111-1)*K111),"")
A112: 46282 | B112: Beaudesert | C112: 9 | D112: 7 | E112: Ed I Am | F112: Lay | G112: Lay | H112: 3.2 | I112: 2.07 | J112: -0.0618 | K112: 1 | L112: 1 | M112: Loss | N112: =IF(M112="Win",IF(F112="Bet",(I112-1)*K112,K112),IF(M112="Loss",IF(F112="Bet",-K112,-(I112-1)*K112),IF(M112="Void",0,""))) | O112: =IF(OR(M112="Win",M112="Loss"),IF(F112="Bet",K112,(I112-1)*K112),"")
A113: 46282 | B113: Bunbury | C113: 7 | D113: 4 | E113: Bondi Star | F113: Lay | G113: Lay | H113: 4.7 | I113: 3.4 | J113: -0.0651 | K113: 1 | L113: 3 | M113: Win | N113: =IF(M113="Win",IF(F113="Bet",(I113-1)*K113,K113),IF(M113="Loss",IF(F113="Bet",-K113,-(I113-1)*K113),IF(M113="Void",0,""))) | O113: =IF(OR(M113="Win",M113="Loss"),IF(F113="Bet",K113,(I113-1)*K113),"")
A114: 46282 | B114: Bunbury | C114: 8 | D114: 10 | E114: Looks | F114: Lay | G114: Lay | H114: 6.8 | I114: 4.6 | J114: -0.0696 | K114: 1 | L114: 8 | M114: Win | N114: =IF(M114="Win",IF(F114="Bet",(I114-1)*K114,K114),IF(M114="Loss",IF(F114="Bet",-K114,-(I114-1)*K114),IF(M114="Void",0,""))) | O114: =IF(OR(M114="Win",M114="Loss"),IF(F114="Bet",K114,(I114-1)*K114),"")
A115: 46283 | B115: Canberra | C115: 2 | D115: 2 | E115: Inna Zou | F115: Lay | G115: Lay | H115: 5.5 | I115: 3.3 | J115: -0.074 | K115: 1 | L115: 2 | M115: Win | N115: =IF(M115="Win",IF(F115="Bet",(I115-1)*K115,K115),IF(M115="Loss",IF(F115="Bet",-K115,-(I115-1)*K115),IF(M115="Void",0,""))) | O115: =IF(OR(M115="Win",M115="Loss"),IF(F115="Bet",K115,(I115-1)*K115),"")
A116: 46283 | B116: Newcastle | C116: 7 | D116: 12 | E116: Mr Miller | F116: Lay | G116: Lay | H116: 3.5 | I116: 1.68 | J116: -0.105 | K116: 1 | L116: 3 | M116: Win | N116: =IF(M116="Win",IF(F116="Bet",(I116-1)*K116,K116),IF(M116="Loss",IF(F116="Bet",-K116,-(I116-1)*K116),IF(M116="Void",0,""))) | O116: =IF(OR(M116="Win",M116="Loss"),IF(F116="Bet",K116,(I116-1)*K116),"")
A117: 46283 | B117: Ballarat | C117: 1 | D117: 5 | E117: Aryaam | F117: Lay | G117: Lay | H117: 4 | I117: 3.2 | J117: -0.0604 | K117: 1 | M117: Void | N117: =IF(M117="Win",IF(F117="Bet",(I117-1)*K117,K117),IF(M117="Loss",IF(F117="Bet",-K117,-(I117-1)*K117),IF(M117="Void",0,""))) | O117: =IF(OR(M117="Win",M117="Loss"),IF(F117="Bet",K117,(I117-1)*K117),"")
A118: 46283 | B118: Canberra | C118: 6 | D118: 11 | E118: Hello G'day | F118: Lay | G118: Lay | H118: 3.1 | I118: 1.47 | J118: -0.0745 | K118: 1 | L118: 3 | M118: Win | N118: =IF(M118="Win",IF(F118="Bet",(I118-1)*K118,K118),IF(M118="Loss",IF(F118="Bet",-K118,-(I118-1)*K118),IF(M118="Void",0,""))) | O118: =IF(OR(M118="Win",M118="Loss"),IF(F118="Bet",K118,(I118-1)*K118),"")
A119: 46283 | B119: Canberra | C119: 7 | D119: 2 | E119: Vella's Best | F119: Lay | G119: Lay | H119: 4.1 | I119: 2.76 | J119: -0.0614 | K119: 1 | L119: 11 | M119: Win | N119: =IF(M119="Win",IF(F119="Bet",(I119-1)*K119,K119),IF(M119="Loss",IF(F119="Bet",-K119,-(I119-1)*K119),IF(M119="Void",0,""))) | O119: =IF(OR(M119="Win",M119="Loss"),IF(F119="Bet",K119,(I119-1)*K119),"")
A120: 46283 | B120: Canberra | C120: 8 | D120: 10 | E120: Judith's Revenge | F120: Lay | G120: Lay | H120: 2 | I120: 1.75 | J120: -0.0701 | K120: 1 | L120: 4 | M120: Win | N120: =IF(M120="Win",IF(F120="Bet",(I120-1)*K120,K120),IF(M120="Loss",IF(F120="Bet",-K120,-(I120-1)*K120),IF(M120="Void",0,""))) | O120: =IF(OR(M120="Win",M120="Loss"),IF(F120="Bet",K120,(I120-1)*K120),"")
A121: 46283 | B121: Canberra | C121: 3 | D121: 2 | E121: Feazabeel | F121: Lay | G121: Lay | H121: 2.3 | I121: 1.78 | J121: -0.0645 | K121: 1 | L121: 1 | M121: Loss | N121: =IF(M121="Win",IF(F121="Bet",(I121-1)*K121,K121),IF(M121="Loss",IF(F121="Bet",-K121,-(I121-1)*K121),IF(M121="Void",0,""))) | O121: =IF(OR(M121="Win",M121="Loss"),IF(F121="Bet",K121,(I121-1)*K121),"")
A122: 46283 | B122: Newcastle | C122: 1 | D122: 4 | E122: Tacitly | F122: Lay | G122: Lay | H122: 5.1 | I122: 3.7 | J122: -0.0759 | K122: 1 | L122: 2 | M122: Win | N122: =IF(M122="Win",IF(F122="Bet",(I122-1)*K122,K122),IF(M122="Loss",IF(F122="Bet",-K122,-(I122-1)*K122),IF(M122="Void",0,""))) | O122: =IF(OR(M122="Win",M122="Loss"),IF(F122="Bet",K122,(I122-1)*K122),"")
A123: 46283 | B123: Canberra | C123: 1 | D123: 1 | E123: Liyah's Girl | F123: Lay | G123: Lay | H123: 3.6 | I123: 2.74 | J123: -0.0855 | K123: 1 | L123: 2 | M123: Win | N123: =IF(M123="Win",IF(F123="Bet",(I123-1)*K123,K123),IF(M123="Loss",IF(F123="Bet",-K123,-(I123-1)*K123),IF(M123="Void",0,""))) | O123: =IF(OR(M123="Win",M123="Loss"),IF(F123="Bet",K123,(I123-1)*K123),"")
A124: 46283 | B124: Townsville | C124: 8 | D124: 4 | E124: Metalcraft | F124: Lay | G124: Lay | H124: 8.5 | I124: 1.6 | J124: -0.4085 | K124: 1 | L124: 1 | M124: Loss | N124: =IF(M124="Win",IF(F124="Bet",(I124-1)*K124,K124),IF(M124="Loss",IF(F124="Bet",-K124,-(I124-1)*K124),IF(M124="Void",0,""))) | O124: =IF(OR(M124="Win",M124="Loss"),IF(F124="Bet",K124,(I124-1)*K124),"")
A125: 46283 | B125: Townsville | C125: 5 | D125: 8 | E125: Red Feathers | F125: Lay | G125: Lay | H125: 4.1 | I125: 1.95 | J125: -0.0908 | K125: 1 | L125: 10 | M125: Win | N125: =IF(M125="Win",IF(F125="Bet",(I125-1)*K125,K125),IF(M125="Loss",IF(F125="Bet",-K125,-(I125-1)*K125),IF(M125="Void",0,""))) | O125: =IF(OR(M125="Win",M125="Loss"),IF(F125="Bet",K125,(I125-1)*K125),"")
A126: 46283 | B126: Newcastle | C126: 8 | D126: 5 | E126: Red Rags To Bulls | F126: Lay | G126: Lay | H126: 5.2 | I126: 3.3 | J126: -0.0635 | K126: 1 | L126: 2 | M126: Win | N126: =IF(M126="Win",IF(F126="Bet",(I126-1)*K126,K126),IF(M126="Loss",IF(F126="Bet",-K126,-(I126-1)*K126),IF(M126="Void",0,""))) | O126: =IF(OR(M126="Win",M126="Loss"),IF(F126="Bet",K126,(I126-1)*K126),"")
A127: 46283 | B127: Ballarat | C127: 9 | D127: 7 | E127: Autumn In Grinzing | F127: Lay | G127: Lay | H127: 4.6 | I127: 2.92 | J127: -0.0907 | K127: 1 | L127: 7 | M127: Win | N127: =IF(M127="Win",IF(F127="Bet",(I127-1)*K127,K127),IF(M127="Loss",IF(F127="Bet",-K127,-(I127-1)*K127),IF(M127="Void",0,""))) | O127: =IF(OR(M127="Win",M127="Loss"),IF(F127="Bet",K127,(I127-1)*K127),"")
A128: 46283 | B128: Ballarat | C128: 4 | D128: 13 | E128: Expensive Taste | F128: Lay | G128: Lay | H128: 5.9 | I128: 4.2 | J128: -0.063 | K128: 1 | L128: 6 | M128: Win | N128: =IF(M128="Win",IF(F128="Bet",(I128-1)*K128,K128),IF(M128="Loss",IF(F128="Bet",-K128,-(I128-1)*K128),IF(M128="Void",0,""))) | O128: =IF(OR(M128="Win",M128="Loss"),IF(F128="Bet",K128,(I128-1)*K128),"")
A129: 46283 | B129: Townsville | C129: 1 | D129: 5 | E129: Red Scentsation | F129: Lay | G129: Lay | H129: 3.7 | I129: 2.94 | J129: -0.0665 | K129: 1 | L129: 3 | M129: Win | N129: =IF(M129="Win",IF(F129="Bet",(I129-1)*K129,K129),IF(M129="Loss",IF(F129="Bet",-K129,-(I129-1)*K129),IF(M129="Void",0,""))) | O129: =IF(OR(M129="Win",M129="Loss"),IF(F129="Bet",K129,(I129-1)*K129),"")
... A155: 46284 | B155: Eagle Farm | C155: 5 | D155: 6 | E155: Esha | F155: Lay | G155: Lay | H155: 2.1 | I155: 1.57 | J155: -0.0778 | K155: 1 | L155: 1 | M155: Loss | N155: =IF(M155="Win",IF(F155="Bet",(I155-1)*K155,K155),IF(M155="Loss",IF(F155="Bet",-K155,-(I155-1)*K155),IF(M155="Void",0,""))) | O155: =IF(OR(M155="Win",M155="Loss"),IF(F155="Bet",K155,(I155-1)*K155),"")
A156: 46284 | B156: Eagle Farm | C156: 8 | D156: 12 | E156: Vincley | F156: Lay | G156: Lay | H156: 5.2 | I156: 3.8 | J156: -0.0695 | K156: 1 | M156: Void | N156: =IF(M156="Win",IF(F156="Bet",(I156-1)*K156,K156),IF(M156="Loss",IF(F156="Bet",-K156,-(I156-1)*K156),IF(M156="Void",0,""))) | O156: =IF(OR(M156="Win",M156="Loss"),IF(F156="Bet",K156,(I156-1)*K156),"")
A157: 46284 | B157: Newcastle | C157: 1 | D157: 8 | E157: Excelluna | F157: Lay | G157: Lay | H157: 3.2 | I157: 2.6 | J157: -0.0697 | K157: 1 | L157: 1 | M157: Loss | N157: =IF(M157="Win",IF(F157="Bet",(I157-1)*K157,K157),IF(M157="Loss",IF(F157="Bet",-K157,-(I157-1)*K157),IF(M157="Void",0,""))) | O157: =IF(OR(M157="Win",M157="Loss"),IF(F157="Bet",K157,(I157-1)*K157),"")
A158: 46284 | B158: Newcastle | C158: 2 | D158: 7 | E158: Klocke | F158: Lay | G158: Lay | H158: 2.05 | I158: 1.41 | J158: -0.0675 | K158: 1 | L158: 2 | M158: Win | N158: =IF(M158="Win",IF(F158="Bet",(I158-1)*K158,K158),IF(M158="Loss",IF(F158="Bet",-K158,-(I158-1)*K158),IF(M158="Void",0,""))) | O158: =IF(OR(M158="Win",M158="Loss"),IF(F158="Bet",K158,(I158-1)*K158),"")
A159: 46284 | B159: Gold Coast | C159: 7 | D159: 1 | E159: Grand Impact | F159: Lay | G159: Lay | H159: 3.3 | I159: 2.48 | J159: -0.0709 | K159: 1 | L159: 5 | M159: Win | N159: =IF(M159="Win",IF(F159="Bet",(I159-1)*K159,K159),IF(M159="Loss",IF(F159="Bet",-K159,-(I159-1)*K159),IF(M159="Void",0,""))) | O159: =IF(OR(M159="Win",M159="Loss"),IF(F159="Bet",K159,(I159-1)*K159),"")
A160: 46284 | B160: Wagga | C160: 2 | D160: 9 | E160: El Cool Gee | F160: Lay | G160: Lay | H160: 3.3 | I160: 2.65 | J160: -0.0634 | K160: 1 | L160: 2 | M160: Win | N160: =IF(M160="Win",IF(F160="Bet",(I160-1)*K160,K160),IF(M160="Loss",IF(F160="Bet",-K160,-(I160-1)*K160),IF(M160="Void",0,""))) | O160: =IF(OR(M160="Win",M160="Loss"),IF(F160="Bet",K160,(I160-1)*K160),"")
A161: 46284 | B161: Morphettville Parks | C161: 9 | D161: 2 | E161: Nicish | F161: Lay | G161: Lay | H161: 4 | I161: 2.96 | J161: -0.0687 | K161: 1 | L161: 9 | M161: Win | N161: =IF(M161="Win",IF(F161="Bet",(I161-1)*K161,K161),IF(M161="Loss",IF(F161="Bet",-K161,-(I161-1)*K161),IF(M161="Void",0,""))) | O161: =IF(OR(M161="Win",M161="Loss"),IF(F161="Bet",K161,(I161-1)*K161),"")
A162: 46284 | B162: Caulfield | C162: 7 | D162: 1 | E162: Lindermann | F162: Lay | G162: Lay | H162: 3.7 | I162: 2.72 | J162: -0.0621 | K162: 1 | L162: 8 | M162: Win | N162: =IF(M162="Win",IF(F162="Bet",(I162-1)*K162,K162),IF(M162="Loss",IF(F162="Bet",-K162,-(I162-1)*K162),IF(M162="Void",0,""))) | O162: =IF(OR(M162="Win",M162="Loss"),IF(F162="Bet",K162,(I162-1)*K162),"")
A163: 46284 | B163: Randwick | C163: 7 | D163: 3 | E163: Striking Alibi | F163: Lay | G163: Lay | H163: 5.5 | I163: 3.1 | J163: -0.0807 | K163: 1 | L163: 2 | M163: Win | N163: =IF(M163="Win",IF(F163="Bet",(I163-1)*K163,K163),IF(M163="Loss",IF(F163="Bet",-K163,-(I163-1)*K163),IF(M163="Void",0,""))) | O163: =IF(OR(M163="Win",M163="Loss"),IF(F163="Bet",K163,(I163-1)*K163),"")
A164: 46284 | B164: Gold Coast | C164: 2 | D164: 4 | E164: Weownachevy | F164: Lay | G164: Lay | H164: 4.3 | I164: 2.98 | J164: -0.0983 | K164: 1 | L164: 1 | M164: Loss | N164: =IF(M164="Win",IF(F164="Bet",(I164-1)*K164,K164),IF(M164="Loss",IF(F164="Bet",-K164,-(I164-1)*K164),IF(M164="Void",0,""))) | O164: =IF(OR(M164="Win",M164="Loss"),IF(F164="Bet",K164,(I164-1)*K164),"")
A165: 46284 | B165: Bowraville | C165: 7 | D165: 7 | E165: Enzoni | F165: Lay | G165: Lay | H165: 5.4 | I165: 3.35 | J165: -0.0759 | K165: 1 | L165: 5 | M165: Win | N165: =IF(M165="Win",IF(F165="Bet",(I165-1)*K165,K165),IF(M165="Loss",IF(F165="Bet",-K165,-(I165-1)*K165),IF(M165="Void",0,""))) | O165: =IF(OR(M165="Win",M165="Loss"),IF(F165="Bet",K165,(I165-1)*K165),"")
A166: 46284 | B166: Belmont | C166: 3 | D166: 1 | E166: Ginnivan | F166: Lay | G166: Lay | H166: 6 | I166: 3.2 | J166: -0.0601 | K166: 1 | L166: 7 | M166: Win | N166: =IF(M166="Win",IF(F166="Bet",(I166-1)*K166,K166),IF(M166="Loss",IF(F166="Bet",-K166,-(I166-1)*K166),IF(M166="Void",0,""))) | O166: =IF(OR(M166="Win",M166="Loss"),IF(F166="Bet",K166,(I166-1)*K166),"")
A167: 46284 | B167: Mt Magnet | C167: 6 | D167: 1 | E167: Another Nephew | F167: Lay | G167: Lay | H167: 2.9 | I167: 2.15 | J167: -0.0859 | K167: 1 | M167: Void | N167: =IF(M167="Win",IF(F167="Bet",(I167-1)*K167,K167),IF(M167="Loss",IF(F167="Bet",-K167,-(I167-1)*K167),IF(M167="Void",0,""))) | O167: =IF(OR(M167="Win",M167="Loss"),IF(F167="Bet",K167,(I167-1)*K167),"")
A168: 46284 | B168: Randwick | C168: 5 | D168: 1 | E168: Headley Grange | F168: Lay | G168: Lay | H168: 3.9 | I168: 3 | J168: -0.0797 | K168: 1 | L168: 3 | M168: Win | N168: =IF(M168="Win",IF(F168="Bet",(I168-1)*K168,K168),IF(M168="Loss",IF(F168="Bet",-K168,-(I168-1)*K168),IF(M168="Void",0,""))) | O168: =IF(OR(M168="Win",M168="Loss"),IF(F168="Bet",K168,(I168-1)*K168),"")
A169: 46284 | B169: Gold Coast | C169: 1 | D169: 5 | E169: Yes Donald Yes | F169: Lay | G169: Lay | H169: 5.2 | I169: 2.57 | J169: -0.0626 | K169: 1 | L169: 2 | M169: Win | N169: =IF(M169="Win",IF(F169="Bet",(I169-1)*K169,K169),IF(M169="Loss",IF(F169="Bet",-K169,-(I169-1)*K169),IF(M169="Void",0,""))) | O169: =IF(OR(M169="Win",M169="Loss"),IF(F169="Bet",K169,(I169-1)*K169),"")
A170: 46284 | B170: Eagle Farm | C170: 8 | D170: 11 | E170: Olivoni | F170: Lay | G170: Lay | H170: 3.4 | I170: 1.71 | J170: -0.094 | K170: 1 | L170: 2 | M170: Win | N170: =IF(M170="Win",IF(F170="Bet",(I170-1)*K170,K170),IF(M170="Loss",IF(F170="Bet",-K170,-(I170-1)*K170),IF(M170="Void",0,""))) | O170: =IF(OR(M170="Win",M170="Loss"),IF(F170="Bet",K170,(I170-1)*K170),"")
A171: 46284 | B171: Echuca | C171: 4 | D171: 5 | E171: Makusha | F171: Lay | G171: Lay | H171: 4.8 | I171: 2.23 | J171: -0.0696 | K171: 1 | L171: 3 | M171: Win | N171: =IF(M171="Win",IF(F171="Bet",(I171-1)*K171,K171),IF(M171="Loss",IF(F171="Bet",-K171,-(I171-1)*K171),IF(M171="Void",0,""))) | O171: =IF(OR(M171="Win",M171="Loss"),IF(F171="Bet",K171,(I171-1)*K171),"")
A172: 46284 | B172: Eagle Farm | C172: 6 | D172: 10 | E172: Russian Ripper | F172: Lay | G172: Lay | H172: 5.7 | I172: 3.6 | J172: -0.0838 | K172: 1 | L172: 4 | M172: Win | N172: =IF(M172="Win",IF(F172="Bet",(I172-1)*K172,K172),IF(M172="Loss",IF(F172="Bet",-K172,-(I172-1)*K172),IF(M172="Void",0,""))) | O172: =IF(OR(M172="Win",M172="Loss"),IF(F172="Bet",K172,(I172-1)*K172),"")
A173: 46284 | B173: Belmont | C173: 1 | D173: 1 | E173: Dawn Dancer | F173: Lay | G173: Lay | H173: 2.6 | I173: 2 | J173: -0.067 | K173: 1 | L173: 1 | M173: Loss | N173: =IF(M173="Win",IF(F173="Bet",(I173-1)*K173,K173),IF(M173="Loss",IF(F173="Bet",-K173,-(I173-1)*K173),IF(M173="Void",0,""))) | O173: =IF(OR(M173="Win",M173="Loss"),IF(F173="Bet",K173,(I173-1)*K173),"")
A174: 46284 | B174: Belmont | C174: 4 | D174: 2 | E174: Royal Toronado | F174: Lay | G174: Lay | H174: 3.4 | I174: 2.7 | J174: -0.0727 | K174: 1 | L174: 3 | M174: Win | N174: =IF(M174="Win",IF(F174="Bet",(I174-1)*K174,K174),IF(M174="Loss",IF(F174="Bet",-K174,-(I174-1)*K174),IF(M174="Void",0,""))) | O174: =IF(OR(M174="Win",M174="Loss"),IF(F174="Bet",K174,(I174-1)*K174),"")
A175: 46284 | B175: Caulfield | C175: 10 | D175: 17 | E175: Cruiserweight | F175: Lay | G175: Lay | H175: 3.9 | I175: 2.98 | J175: -0.0686 | K175: 1 | L175: 7 | M175: Win | N175: =IF(M175="Win",IF(F175="Bet",(I175-1)*K175,K175),IF(M175="Loss",IF(F175="Bet",-K175,-(I175-1)*K175),IF(M175="Void",0,""))) | O175: =IF(OR(M175="Win",M175="Loss"),IF(F175="Bet",K175,(I175-1)*K175),"")
A176: 46284 | B176: Newcastle | C176: 6 | D176: 2 | E176: Oakfield Utah | F176: Lay | G176: Lay | H176: 5.6 | I176: 4 | J176: -0.0708 | K176: 1 | L176: 1 | M176: Loss | N176: =IF(M176="Win",IF(F176="Bet",(I176-1)*K176,K176),IF(M176="Loss",IF(F176="Bet",-K176,-(I176-1)*K176),IF(M176="Void",0,""))) | O176: =IF(OR(M176="Win",M176="Loss"),IF(F176="Bet",K176,(I176-1)*K176),"")
A177: 46284 | B177: Caulfield | C177: 3 | D177: 2 | E177: Winnasedge | F177: Lay | G177: Lay | H177: 6.7 | I177: 4.4 | J177: -0.0628 | K177: 1 | L177: 7 | M177: Win | N177: =IF(M177="Win",IF(F177="Bet",(I177-1)*K177,K177),IF(M177="Loss",IF(F177="Bet",-K177,-(I177-1)*K177),IF(M177="Void",0,""))) | O177: =IF(OR(M177="Win",M177="Loss"),IF(F177="Bet",K177,(I177-1)*K177),"")
A178: 46284 | B178: Caulfield | C178: 5 | D178: 3 | E178: Blind Raise | F178: Lay | G178: Lay | H178: 3.5 | I178: 2.47 | J178: -0.0644 | K178: 1 | L178: 1 | M178: Loss | N178: =IF(M178="Win",IF(F178="Bet",(I178-1)*K178,K178),IF(M178="Loss",IF(F178="Bet",-K178,-(I178-1)*K178),IF(M178="Void",0,""))) | O178: =IF(OR(M178="Win",M178="Loss"),IF(F178="Bet",K178,(I178-1)*K178),"")
A179: 46284 | B179: Gold Coast | C179: 6 | D179: 12 | E179: Spirit Of Barty | F179: Lay | G179: Lay | H179: 3.8 | I179: 2.67 | J179: -0.1051 | K179: 1 | L179: 1 | M179: Loss | N179: =IF(M179="Win",IF(F179="Bet",(I179-1)*K179,K179),IF(M179="Loss",IF(F179="Bet",-K179,-(I179-1)*K179),IF(M179="Void",0,""))) | O179: =IF(OR(M179="Win",M179="Loss"),IF(F179="Bet",K179,(I179-1)*K179),"")
... A195: 46284 | B195: Bowraville | C195: 4 | D195: 3 | E195: Dipierdomenico | F195: Lay | G195: Lay | H195: 3.7 | I195: 2.71 | J195: -0.0769 | K195: 1 | L195: 1 | M195: Loss | N195: =IF(M195="Win",IF(F195="Bet",(I195-1)*K195,K195),IF(M195="Loss",IF(F195="Bet",-K195,-(I195-1)*K195),IF(M195="Void",0,""))) | O195: =IF(OR(M195="Win",M195="Loss"),IF(F195="Bet",K195,(I195-1)*K195),"")
A196: 46284 | B196: Mt Magnet | C196: 1 | D196: 6 | E196: Principal Dealer | F196: Lay | G196: Lay | H196: 6.9 | I196: 4.4 | J196: -0.0734 | K196: 1 | M196: Void | N196: =IF(M196="Win",IF(F196="Bet",(I196-1)*K196,K196),IF(M196="Loss",IF(F196="Bet",-K196,-(I196-1)*K196),IF(M196="Void",0,""))) | O196: =IF(OR(M196="Win",M196="Loss"),IF(F196="Bet",K196,(I196-1)*K196),"")
A197: 46284 | B197: Echuca | C197: 7 | D197: 3 | E197: Manchego | F197: Lay | G197: Lay | H197: 4.6 | I197: 2.46 | J197: -0.0946 | K197: 1 | L197: 1 | M197: Loss | N197: =IF(M197="Win",IF(F197="Bet",(I197-1)*K197,K197),IF(M197="Loss",IF(F197="Bet",-K197,-(I197-1)*K197),IF(M197="Void",0,""))) | O197: =IF(OR(M197="Win",M197="Loss"),IF(F197="Bet",K197,(I197-1)*K197),"")
A198: 46284 | B198: Belmont | C198: 7 | D198: 11 | E198: Marcos | F198: Lay | G198: Lay | H198: 6.4 | I198: 3.95 | J198: -0.0621 | K198: 1 | L198: 1 | M198: Loss | N198: =IF(M198="Win",IF(F198="Bet",(I198-1)*K198,K198),IF(M198="Loss",IF(F198="Bet",-K198,-(I198-1)*K198),IF(M198="Void",0,""))) | O198: =IF(OR(M198="Win",M198="Loss"),IF(F198="Bet",K198,(I198-1)*K198),"")
A199: 46284 | B199: Eagle Farm | C199: 7 | D199: 18 | E199: Mana Combat | F199: Lay | G199: Lay | H199: 8.5 | I199: 5.13 | J199: -0.0612 | K199: 1 | L199: 3 | M199: Win | N199: =IF(M199="Win",IF(F199="Bet",(I199-1)*K199,K199),IF(M199="Loss",IF(F199="Bet",-K199,-(I199-1)*K199),IF(M199="Void",0,""))) | O199: =IF(OR(M199="Win",M199="Loss"),IF(F199="Bet",K199,(I199-1)*K199),"")
A200: 46284 | B200: Caulfield | C200: 9 | D200: 6 | E200: Lady Shenandoah | F200: Lay | G200: Lay | H200: 6 | I200: 4.2 | J200: -0.0721 | K200: 1 | L200: 4 | M200: Win | N200: =IF(M200="Win",IF(F200="Bet",(I200-1)*K200,K200),IF(M200="Loss",IF(F200="Bet",-K200,-(I200-1)*K200),IF(M200="Void",0,""))) | O200: =IF(OR(M200="Win",M200="Loss"),IF(F200="Bet",K200,(I200-1)*K200),"")
A201: 46284 | B201: Caulfield | C201: 10 | D201: 19 | E201: Savoyard | F201: Lay | G201: Lay | H201: 5.3 | I201: 4 | J201: -0.0622 | K201: 1 | L201: 4 | M201: Win | N201: =IF(M201="Win",IF(F201="Bet",(I201-1)*K201,K201),IF(M201="Loss",IF(F201="Bet",-K201,-(I201-1)*K201),IF(M201="Void",0,""))) | O201: =IF(OR(M201="Win",M201="Loss"),IF(F201="Bet",K201,(I201-1)*K201),"")
A202: 46284 | B202: Belmont | C202: 4 | D202: 8 | E202: Searchin' Times | F202: Lay | G202: Lay | H202: 8.5 | I202: 5.1 | J202: -0.0645 | K202: 1 | L202: 6 | M202: Win | N202: =IF(M202="Win",IF(F202="Bet",(I202-1)*K202,K202),IF(M202="Loss",IF(F202="Bet",-K202,-(I202-1)*K202),IF(M202="Void",0,""))) | O202: =IF(OR(M202="Win",M202="Loss"),IF(F202="Bet",K202,(I202-1)*K202),"")
A203: 46284 | B203: Darwin | C203: 4 | D203: 1 | E203: Meet Me At The Bar | F203: Lay | G203: Lay | H203: 4.4 | I203: 3.45 | J203: -0.064 | K203: 1 | L203: 5 | M203: Win | N203: =IF(M203="Win",IF(F203="Bet",(I203-1)*K203,K203),IF(M203="Loss",IF(F203="Bet",-K203,-(I203-1)*K203),IF(M203="Void",0,""))) | O203: =IF(OR(M203="Win",M203="Loss"),IF(F203="Bet",K203,(I203-1)*K203),"")
A204: 46284 | B204: Belmont | C204: 8 | D204: 4 | E204: Double The Fun | F204: Lay | G204: Lay | H204: 5.3 | I204: 4 | J204: -0.0628 | K204: 1 | L204: 8 | M204: Win | N204: =IF(M204="Win",IF(F204="Bet",(I204-1)*K204,K204),IF(M204="Loss",IF(F204="Bet",-K204,-(I204-1)*K204),IF(M204="Void",0,""))) | O204: =IF(OR(M204="Win",M204="Loss"),IF(F204="Bet",K204,(I204-1)*K204),"")
A205: 46285 | B205: Armidale | C205: 3 | D205: 7 | E205: Aurora Effect | F205: Lay | G205: Lay | H205: 3.7 | I205: 2.76 | J205: -0.0858 | K205: 1 | L205: 5 | M205: Win | N205: =IF(M205="Win",IF(F205="Bet",(I205-1)*K205,K205),IF(M205="Loss",IF(F205="Bet",-K205,-(I205-1)*K205),IF(M205="Void",0,""))) | O205: =IF(OR(M205="Win",M205="Loss"),IF(F205="Bet",K205,(I205-1)*K205),"")
...
